{"box_data": [{"position": {"minX": 1008.0, "minY": 411.0, "maxX": 1188.0, "maxY": 535.5}, "class_id": 0, "box_caption": "car 0.921", "scores": {"class_score": 0.92138671875}, "domain": "pixel"}, {"position": {"minX": 592.5, "minY": 425.0, "maxX": 741.5, "maxY": 517.5}, "class_id": 0, "box_caption": "car 0.912", "scores": {"class_score": 0.912109375}, "domain": "pixel"}, {"position": {"minX": 948.0, "minY": 423.0, "maxX": 1036.0, "maxY": 495.0}, "class_id": 0, "box_caption": "car 0.872", "scores": {"class_score": 0.87158203125}, "domain": "pixel"}, {"position": {"minX": 795.0, "minY": 421.75, "maxX": 837.0, "maxY": 450.25}, "class_id": 0, "box_caption": "car 0.854", "scores": {"class_score": 0.853515625}, "domain": "pixel"}, {"position": {"minX": 886.0, "minY": 424.75, "maxX": 937.0, "maxY": 461.75}, "class_id": 0, "box_caption": "car 0.809", "scores": {"class_score": 0.80908203125}, "domain": "pixel"}, {"position": {"minX": 713.0, "minY": 419.75, "maxX": 766.0, "maxY": 459.25}, "class_id": 0, "box_caption": "car 0.808", "scores": {"class_score": 0.80810546875}, "domain": "pixel"}, {"position": {"minX": 921.5, "minY": 423.75, "maxX": 980.5, "maxY": 473.75}, "class_id": 0, "box_caption": "car 0.759", "scores": {"class_score": 0.7587890625}, "domain": "pixel"}, {"position": {"minX": 745.5, "minY": 411.5, "maxX": 786.5, "maxY": 449.5}, "class_id": 0, "box_caption": "car 0.665", "scores": {"class_score": 0.6650390625}, "domain": "pixel"}, {"position": {"minX": 838.0, "minY": 414.25, "maxX": 864.0, "maxY": 436.25}, "class_id": 0, "box_caption": "car 0.533", "scores": {"class_score": 0.53271484375}, "domain": "pixel"}, {"position": {"minX": 775.0, "minY": 417.0, "maxX": 798.0, "maxY": 442.0}, "class_id": 0, "box_caption": "car 0.520", "scores": {"class_score": 0.51953125}, "domain": "pixel"}, {"position": {"minX": 859.5, "minY": 422.75, "maxX": 899.5, "maxY": 453.75}, "class_id": 0, "box_caption": "car 0.516", "scores": {"class_score": 0.515625}, "domain": "pixel"}, {"position": {"minX": 846.5, "minY": 416.5, "maxX": 874.5, "maxY": 440.5}, "class_id": 0, "box_caption": "car 0.453", "scores": {"class_score": 0.452880859375}, "domain": "pixel"}, {"position": {"minX": 851.0, "minY": 419.5, "maxX": 888.0, "maxY": 447.5}, "class_id": 0, "box_caption": "car 0.336", "scores": {"class_score": 0.335693359375}, "domain": "pixel"}, {"position": {"minX": 775.0, "minY": 411.0, "maxX": 799.0, "maxY": 434.5}, "class_id": 0, "box_caption": "car 0.252", "scores": {"class_score": 0.251953125}, "domain": "pixel"}, {"position": {"minX": 852.5, "minY": 424.75, "maxX": 894.5, "maxY": 460.25}, "class_id": 0, "box_caption": "car 0.172", "scores": {"class_score": 0.172119140625}, "domain": "pixel"}, {"position": {"minX": 831.5, "minY": 417.0, "maxX": 846.5, "maxY": 436.0}, "class_id": 0, "box_caption": "car 0.171", "scores": {"class_score": 0.17138671875}, "domain": "pixel"}, {"position": {"minX": 778.0, "minY": 409.75, "maxX": 808.0, "maxY": 431.75}, "class_id": 0, "box_caption": "car 0.130", "scores": {"class_score": 0.1295166015625}, "domain": "pixel"}, {"position": {"minX": 858.0, "minY": 421.5, "maxX": 894.0, "maxY": 445.0}, "class_id": 0, "box_caption": "car 0.126", "scores": {"class_score": 0.1258544921875}, "domain": "pixel"}, {"position": {"minX": 787.0, "minY": 404.75, "maxX": 821.0, "maxY": 428.25}, "class_id": 0, "box_caption": "car 0.088", "scores": {"class_score": 0.0877685546875}, "domain": "pixel"}, {"position": {"minX": 853.5, "minY": 413.75, "maxX": 881.5, "maxY": 431.75}, "class_id": 0, "box_caption": "car 0.081", "scores": {"class_score": 0.08111572265625}, "domain": "pixel"}, {"position": {"minX": 847.0, "minY": 424.5, "maxX": 878.0, "maxY": 455.5}, "class_id": 0, "box_caption": "car 0.067", "scores": {"class_score": 0.067138671875}, "domain": "pixel"}, {"position": {"minX": 790.5, "minY": 422.0, "maxX": 811.5, "maxY": 441.5}, "class_id": 0, "box_caption": "car 0.061", "scores": {"class_score": 0.061248779296875}, "domain": "pixel"}, {"position": {"minX": 872.0, "minY": 422.75, "maxX": 901.0, "maxY": 447.75}, "class_id": 0, "box_caption": "car 0.061", "scores": {"class_score": 0.060791015625}, "domain": "pixel"}, {"position": {"minX": 841.0, "minY": 417.0, "maxX": 864.0, "maxY": 443.5}, "class_id": 0, "box_caption": "car 0.055", "scores": {"class_score": 0.054840087890625}, "domain": "pixel"}, {"position": {"minX": 787.0, "minY": 404.5, "maxX": 821.0, "maxY": 429.0}, "class_id": 2, "box_caption": "truck 0.054", "scores": {"class_score": 0.0543212890625}, "domain": "pixel"}, {"position": {"minX": 840.0, "minY": 410.5, "maxX": 878.0, "maxY": 438.5}, "class_id": 0, "box_caption": "car 0.048", "scores": {"class_score": 0.04803466796875}, "domain": "pixel"}, {"position": {"minX": 778.0, "minY": 414.0, "maxX": 805.0, "maxY": 441.5}, "class_id": 0, "box_caption": "car 0.047", "scores": {"class_score": 0.04742431640625}, "domain": "pixel"}, {"position": {"minX": 832.5, "minY": 420.25, "maxX": 844.5, "maxY": 441.75}, "class_id": 0, "box_caption": "car 0.046", "scores": {"class_score": 0.04571533203125}, "domain": "pixel"}, {"position": {"minX": 795.0, "minY": 405.5, "maxX": 824.0, "maxY": 425.5}, "class_id": 2, "box_caption": "truck 0.044", "scores": {"class_score": 0.04376220703125}, "domain": "pixel"}, {"position": {"minX": 785.0, "minY": 421.75, "maxX": 802.0, "maxY": 440.25}, "class_id": 0, "box_caption": "car 0.041", "scores": {"class_score": 0.04144287109375}, "domain": "pixel"}, {"position": {"minX": 750.5, "minY": 420.75, "maxX": 781.5, "maxY": 455.25}, "class_id": 0, "box_caption": "car 0.040", "scores": {"class_score": 0.040496826171875}, "domain": "pixel"}, {"position": {"minX": 828.5, "minY": 412.25, "maxX": 860.5, "maxY": 433.25}, "class_id": 0, "box_caption": "car 0.033", "scores": {"class_score": 0.032928466796875}, "domain": "pixel"}, {"position": {"minX": 858.5, "minY": 406.75, "maxX": 888.5, "maxY": 425.75}, "class_id": 0, "box_caption": "car 0.032", "scores": {"class_score": 0.0316162109375}, "domain": "pixel"}, {"position": {"minX": 839.5, "minY": 412.75, "maxX": 882.5, "maxY": 455.25}, "class_id": 0, "box_caption": "car 0.031", "scores": {"class_score": 0.031402587890625}, "domain": "pixel"}, {"position": {"minX": 664.5, "minY": 371.25, "maxX": 699.5, "maxY": 431.75}, "class_id": 3, "box_caption": "bus 0.030", "scores": {"class_score": 0.0302581787109375}, "domain": "pixel"}, {"position": {"minX": 664.5, "minY": 371.25, "maxX": 699.5, "maxY": 431.75}, "class_id": 8, "box_caption": "caravan 0.028", "scores": {"class_score": 0.0282745361328125}, "domain": "pixel"}, {"position": {"minX": 830.0, "minY": 414.5, "maxX": 848.0, "maxY": 441.0}, "class_id": 0, "box_caption": "car 0.027", "scores": {"class_score": 0.0272064208984375}, "domain": "pixel"}, {"position": {"minX": 667.0, "minY": 372.75, "maxX": 699.0, "maxY": 428.25}, "class_id": 0, "box_caption": "car 0.024", "scores": {"class_score": 0.024078369140625}, "domain": "pixel"}, {"position": {"minX": 834.0, "minY": 419.25, "maxX": 854.0, "maxY": 441.75}, "class_id": 0, "box_caption": "car 0.024", "scores": {"class_score": 0.023681640625}, "domain": "pixel"}, {"position": {"minX": 793.0, "minY": 419.5, "maxX": 834.0, "maxY": 450.5}, "class_id": 2, "box_caption": "truck 0.024", "scores": {"class_score": 0.023681640625}, "domain": "pixel"}, {"position": {"minX": 774.0, "minY": 410.75, "maxX": 805.0, "maxY": 439.25}, "class_id": 2, "box_caption": "truck 0.023", "scores": {"class_score": 0.02264404296875}, "domain": "pixel"}, {"position": {"minX": 902.5, "minY": 424.25, "maxX": 939.5, "maxY": 450.25}, "class_id": 0, "box_caption": "car 0.021", "scores": {"class_score": 0.020660400390625}, "domain": "pixel"}, {"position": {"minX": 876.0, "minY": 422.75, "maxX": 901.0, "maxY": 439.75}, "class_id": 0, "box_caption": "car 0.019", "scores": {"class_score": 0.01873779296875}, "domain": "pixel"}, {"position": {"minX": 754.5, "minY": 411.0, "maxX": 786.5, "maxY": 437.0}, "class_id": 0, "box_caption": "car 0.018", "scores": {"class_score": 0.0181427001953125}, "domain": "pixel"}, {"position": {"minX": 828.5, "minY": 408.25, "maxX": 888.5, "maxY": 448.75}, "class_id": 0, "box_caption": "car 0.018", "scores": {"class_score": 0.01763916015625}, "domain": "pixel"}, {"position": {"minX": 850.0, "minY": 404.0, "maxX": 884.0, "maxY": 439.0}, "class_id": 0, "box_caption": "car 0.018", "scores": {"class_score": 0.0175933837890625}, "domain": "pixel"}, {"position": {"minX": 824.5, "minY": 415.75, "maxX": 837.5, "maxY": 427.25}, "class_id": 0, "box_caption": "car 0.017", "scores": {"class_score": 0.0174560546875}, "domain": "pixel"}, {"position": {"minX": 770.5, "minY": 411.75, "maxX": 788.5, "maxY": 424.75}, "class_id": 0, "box_caption": "car 0.017", "scores": {"class_score": 0.0171051025390625}, "domain": "pixel"}, {"position": {"minX": 870.0, "minY": 425.75, "maxX": 905.0, "maxY": 459.25}, "class_id": 0, "box_caption": "car 0.017", "scores": {"class_score": 0.0166473388671875}, "domain": "pixel"}, {"position": {"minX": 743.0, "minY": 411.75, "maxX": 776.0, "maxY": 431.25}, "class_id": 0, "box_caption": "car 0.016", "scores": {"class_score": 0.016326904296875}, "domain": "pixel"}, {"position": {"minX": 789.0, "minY": 411.0, "maxX": 838.0, "maxY": 453.0}, "class_id": 0, "box_caption": "car 0.016", "scores": {"class_score": 0.0159759521484375}, "domain": "pixel"}, {"position": {"minX": 824.0, "minY": 420.5, "maxX": 839.0, "maxY": 439.5}, "class_id": 0, "box_caption": "car 0.015", "scores": {"class_score": 0.01509857177734375}, "domain": "pixel"}, {"position": {"minX": 750.0, "minY": 423.75, "maxX": 770.0, "maxY": 457.75}, "class_id": 0, "box_caption": "car 0.015", "scores": {"class_score": 0.01482391357421875}, "domain": "pixel"}, {"position": {"minX": 843.5, "minY": 426.75, "maxX": 864.5, "maxY": 452.25}, "class_id": 0, "box_caption": "car 0.014", "scores": {"class_score": 0.014251708984375}, "domain": "pixel"}, {"position": {"minX": 777.5, "minY": 409.75, "maxX": 808.5, "maxY": 432.25}, "class_id": 2, "box_caption": "truck 0.014", "scores": {"class_score": 0.01377105712890625}, "domain": "pixel"}, {"position": {"minX": 859.0, "minY": 404.5, "maxX": 885.0, "maxY": 425.0}, "class_id": 3, "box_caption": "bus 0.013", "scores": {"class_score": 0.013092041015625}, "domain": "pixel"}, {"position": {"minX": 923.0, "minY": 429.5, "maxX": 943.0, "maxY": 454.0}, "class_id": 0, "box_caption": "car 0.012", "scores": {"class_score": 0.01239013671875}, "domain": "pixel"}, {"position": {"minX": 860.0, "minY": 405.75, "maxX": 882.0, "maxY": 424.75}, "class_id": 2, "box_caption": "truck 0.012", "scores": {"class_score": 0.01183319091796875}, "domain": "pixel"}, {"position": {"minX": 793.5, "minY": 401.25, "maxX": 825.5, "maxY": 431.75}, "class_id": 2, "box_caption": "truck 0.012", "scores": {"class_score": 0.01157379150390625}, "domain": "pixel"}, {"position": {"minX": 787.0, "minY": 404.5, "maxX": 821.0, "maxY": 429.0}, "class_id": 3, "box_caption": "bus 0.011", "scores": {"class_score": 0.01058197021484375}, "domain": "pixel"}, {"position": {"minX": 740.0, "minY": 414.25, "maxX": 761.0, "maxY": 426.25}, "class_id": 0, "box_caption": "car 0.011", "scores": {"class_score": 0.01050567626953125}, "domain": "pixel"}, {"position": {"minX": 664.5, "minY": 371.25, "maxX": 699.5, "maxY": 432.75}, "class_id": 6, "box_caption": "trailer 0.010", "scores": {"class_score": 0.010498046875}, "domain": "pixel"}, {"position": {"minX": 750.0, "minY": 413.0, "maxX": 785.0, "maxY": 453.0}, "class_id": 1, "box_caption": "person 0.010", "scores": {"class_score": 0.01047515869140625}, "domain": "pixel"}, {"position": {"minX": 792.5, "minY": 400.5, "maxX": 834.5, "maxY": 430.0}, "class_id": 0, "box_caption": "car 0.010", "scores": {"class_score": 0.01041412353515625}, "domain": "pixel"}, {"position": {"minX": 925.0, "minY": 426.75, "maxX": 955.0, "maxY": 451.25}, "class_id": 0, "box_caption": "car 0.010", "scores": {"class_score": 0.0101776123046875}, "domain": "pixel"}, {"position": {"minX": 854.0, "minY": 427.5, "maxX": 896.0, "maxY": 465.0}, "class_id": 7, "box_caption": "motorcycle 0.010", "scores": {"class_score": 0.0100555419921875}, "domain": "pixel"}, {"position": {"minX": 938.5, "minY": 423.5, "maxX": 984.5, "maxY": 450.0}, "class_id": 0, "box_caption": "car 0.009", "scores": {"class_score": 0.00890350341796875}, "domain": "pixel"}, {"position": {"minX": 857.0, "minY": 424.0, "maxX": 915.0, "maxY": 461.5}, "class_id": 0, "box_caption": "car 0.009", "scores": {"class_score": 0.00888824462890625}, "domain": "pixel"}, {"position": {"minX": 769.5, "minY": 403.75, "maxX": 810.5, "maxY": 445.75}, "class_id": 0, "box_caption": "car 0.009", "scores": {"class_score": 0.00865936279296875}, "domain": "pixel"}, {"position": {"minX": 664.5, "minY": 371.25, "maxX": 699.5, "maxY": 431.75}, "class_id": 2, "box_caption": "truck 0.008", "scores": {"class_score": 0.0081634521484375}, "domain": "pixel"}, {"position": {"minX": 829.5, "minY": 416.5, "maxX": 845.5, "maxY": 431.5}, "class_id": 1, "box_caption": "person 0.008", "scores": {"class_score": 0.008026123046875}, "domain": "pixel"}, {"position": {"minX": 774.0, "minY": 410.75, "maxX": 805.0, "maxY": 439.25}, "class_id": 3, "box_caption": "bus 0.008", "scores": {"class_score": 0.00797271728515625}, "domain": "pixel"}, {"position": {"minX": 918.5, "minY": 429.5, "maxX": 964.5, "maxY": 480.0}, "class_id": 0, "box_caption": "car 0.007", "scores": {"class_score": 0.007381439208984375}, "domain": "pixel"}, {"position": {"minX": 862.0, "minY": 428.0, "maxX": 900.0, "maxY": 464.0}, "class_id": 0, "box_caption": "car 0.007", "scores": {"class_score": 0.007274627685546875}, "domain": "pixel"}, {"position": {"minX": 892.5, "minY": 424.25, "maxX": 937.5, "maxY": 439.75}, "class_id": 0, "box_caption": "car 0.007", "scores": {"class_score": 0.006954193115234375}, "domain": "pixel"}, {"position": {"minX": 925.0, "minY": 433.5, "maxX": 945.0, "maxY": 465.5}, "class_id": 0, "box_caption": "car 0.007", "scores": {"class_score": 0.006946563720703125}, "domain": "pixel"}, {"position": {"minX": 920.5, "minY": 426.5, "maxX": 943.5, "maxY": 447.0}, "class_id": 0, "box_caption": "car 0.007", "scores": {"class_score": 0.00665283203125}, "domain": "pixel"}, {"position": {"minX": 766.0, "minY": 412.25, "maxX": 782.0, "maxY": 422.75}, "class_id": 0, "box_caption": "car 0.006", "scores": {"class_score": 0.006317138671875}, "domain": "pixel"}, {"position": {"minX": 793.0, "minY": 419.5, "maxX": 834.0, "maxY": 450.5}, "class_id": 3, "box_caption": "bus 0.006", "scores": {"class_score": 0.00628662109375}, "domain": "pixel"}, {"position": {"minX": 919.5, "minY": 426.5, "maxX": 945.5, "maxY": 459.0}, "class_id": 0, "box_caption": "car 0.006", "scores": {"class_score": 0.006229400634765625}, "domain": "pixel"}, {"position": {"minX": 855.5, "minY": 401.5, "maxX": 891.5, "maxY": 434.0}, "class_id": 0, "box_caption": "car 0.006", "scores": {"class_score": 0.00620269775390625}, "domain": "pixel"}, {"position": {"minX": 920.0, "minY": 423.25, "maxX": 960.0, "maxY": 456.25}, "class_id": 0, "box_caption": "car 0.006", "scores": {"class_score": 0.006175994873046875}, "domain": "pixel"}, {"position": {"minX": 936.5, "minY": 428.0, "maxX": 989.5, "maxY": 483.0}, "class_id": 0, "box_caption": "car 0.006", "scores": {"class_score": 0.006137847900390625}, "domain": "pixel"}, {"position": {"minX": 779.5, "minY": 416.75, "maxX": 803.5, "maxY": 440.25}, "class_id": 1, "box_caption": "person 0.006", "scores": {"class_score": 0.006103515625}, "domain": "pixel"}, {"position": {"minX": 822.5, "minY": 413.75, "maxX": 839.5, "maxY": 428.75}, "class_id": 0, "box_caption": "car 0.006", "scores": {"class_score": 0.00601959228515625}, "domain": "pixel"}, {"position": {"minX": 800.5, "minY": 408.75, "maxX": 836.5, "maxY": 426.75}, "class_id": 0, "box_caption": "car 0.006", "scores": {"class_score": 0.005970001220703125}, "domain": "pixel"}, {"position": {"minX": 924.0, "minY": 420.75, "maxX": 982.0, "maxY": 454.75}, "class_id": 0, "box_caption": "car 0.006", "scores": {"class_score": 0.005970001220703125}, "domain": "pixel"}, {"position": {"minX": 731.0, "minY": 418.25, "maxX": 768.0, "maxY": 446.25}, "class_id": 0, "box_caption": "car 0.006", "scores": {"class_score": 0.00595855712890625}, "domain": "pixel"}, {"position": {"minX": 664.5, "minY": 371.25, "maxX": 699.5, "maxY": 432.75}, "class_id": 9, "box_caption": "train 0.006", "scores": {"class_score": 0.00563812255859375}, "domain": "pixel"}, {"position": {"minX": 871.0, "minY": 409.25, "maxX": 894.0, "maxY": 425.75}, "class_id": 0, "box_caption": "car 0.006", "scores": {"class_score": 0.0056304931640625}, "domain": "pixel"}, {"position": {"minX": 795.0, "minY": 405.5, "maxX": 824.0, "maxY": 425.5}, "class_id": 3, "box_caption": "bus 0.006", "scores": {"class_score": 0.00557708740234375}, "domain": "pixel"}, {"position": {"minX": 775.5, "minY": 417.0, "maxX": 797.5, "maxY": 442.0}, "class_id": 2, "box_caption": "truck 0.005", "scores": {"class_score": 0.005466461181640625}, "domain": "pixel"}, {"position": {"minX": 783.0, "minY": 418.75, "maxX": 804.0, "maxY": 445.25}, "class_id": 0, "box_caption": "car 0.005", "scores": {"class_score": 0.00545501708984375}, "domain": "pixel"}, {"position": {"minX": 857.5, "minY": 405.0, "maxX": 889.5, "maxY": 427.5}, "class_id": 2, "box_caption": "truck 0.005", "scores": {"class_score": 0.005413055419921875}, "domain": "pixel"}, {"position": {"minX": 747.5, "minY": 411.75, "maxX": 786.5, "maxY": 450.25}, "class_id": 2, "box_caption": "truck 0.005", "scores": {"class_score": 0.00502777099609375}, "domain": "pixel"}, {"position": {"minX": 908.5, "minY": 414.5, "maxX": 1001.5, "maxY": 484.0}, "class_id": 0, "box_caption": "car 0.005", "scores": {"class_score": 0.00501251220703125}, "domain": "pixel"}, {"position": {"minX": 826.5, "minY": 409.75, "maxX": 849.5, "maxY": 436.75}, "class_id": 0, "box_caption": "car 0.005", "scores": {"class_score": 0.004886627197265625}, "domain": "pixel"}, {"position": {"minX": 886.0, "minY": 425.0, "maxX": 938.0, "maxY": 462.0}, "class_id": 2, "box_caption": "truck 0.005", "scores": {"class_score": 0.00484466552734375}, "domain": "pixel"}, {"position": {"minX": 854.0, "minY": 406.0, "maxX": 889.0, "maxY": 429.5}, "class_id": 3, "box_caption": "bus 0.005", "scores": {"class_score": 0.00470733642578125}, "domain": "pixel"}, {"position": {"minX": 1008.0, "minY": 410.5, "maxX": 1188.0, "maxY": 535.5}, "class_id": 2, "box_caption": "truck 0.005", "scores": {"class_score": 0.004650115966796875}, "domain": "pixel"}, {"position": {"minX": 711.0, "minY": 423.0, "maxX": 724.0, "maxY": 436.0}, "class_id": 0, "box_caption": "car 0.005", "scores": {"class_score": 0.004634857177734375}, "domain": "pixel"}, {"position": {"minX": 909.0, "minY": 423.75, "maxX": 939.0, "maxY": 438.25}, "class_id": 0, "box_caption": "car 0.005", "scores": {"class_score": 0.0046234130859375}, "domain": "pixel"}, {"position": {"minX": 777.5, "minY": 409.75, "maxX": 808.5, "maxY": 432.25}, "class_id": 3, "box_caption": "bus 0.004", "scores": {"class_score": 0.00441741943359375}, "domain": "pixel"}, {"position": {"minX": 1007.5, "minY": 410.5, "maxX": 1188.0, "maxY": 535.5}, "class_id": 8, "box_caption": "caravan 0.004", "scores": {"class_score": 0.004398345947265625}, "domain": "pixel"}, {"position": {"minX": 592.5, "minY": 424.75, "maxX": 740.5, "maxY": 518.5}, "class_id": 3, "box_caption": "bus 0.004", "scores": {"class_score": 0.004314422607421875}, "domain": "pixel"}, {"position": {"minX": 592.5, "minY": 424.75, "maxX": 740.5, "maxY": 518.5}, "class_id": 8, "box_caption": "caravan 0.004", "scores": {"class_score": 0.004299163818359375}, "domain": "pixel"}, {"position": {"minX": 921.0, "minY": 428.75, "maxX": 949.0, "maxY": 470.75}, "class_id": 0, "box_caption": "car 0.004", "scores": {"class_score": 0.004283905029296875}, "domain": "pixel"}, {"position": {"minX": 693.5, "minY": 372.5, "maxX": 702.5, "maxY": 419.5}, "class_id": 0, "box_caption": "car 0.004", "scores": {"class_score": 0.004253387451171875}, "domain": "pixel"}, {"position": {"minX": 592.5, "minY": 424.75, "maxX": 740.5, "maxY": 518.5}, "class_id": 2, "box_caption": "truck 0.004", "scores": {"class_score": 0.004245758056640625}, "domain": "pixel"}, {"position": {"minX": 775.5, "minY": 417.0, "maxX": 797.5, "maxY": 442.0}, "class_id": 3, "box_caption": "bus 0.004", "scores": {"class_score": 0.004215240478515625}, "domain": "pixel"}, {"position": {"minX": 834.0, "minY": 413.25, "maxX": 865.0, "maxY": 437.25}, "class_id": 2, "box_caption": "truck 0.004", "scores": {"class_score": 0.004199981689453125}, "domain": "pixel"}, {"position": {"minX": 592.5, "minY": 424.75, "maxX": 740.5, "maxY": 518.5}, "class_id": 1, "box_caption": "person 0.004", "scores": {"class_score": 0.0041961669921875}, "domain": "pixel"}, {"position": {"minX": 851.0, "minY": 419.5, "maxX": 888.0, "maxY": 447.5}, "class_id": 2, "box_caption": "truck 0.004", "scores": {"class_score": 0.004138946533203125}, "domain": "pixel"}, {"position": {"minX": 1007.5, "minY": 410.5, "maxX": 1188.0, "maxY": 535.5}, "class_id": 3, "box_caption": "bus 0.004", "scores": {"class_score": 0.004116058349609375}, "domain": "pixel"}, {"position": {"minX": 592.5, "minY": 424.75, "maxX": 740.5, "maxY": 518.5}, "class_id": 4, "box_caption": "bicycle 0.004", "scores": {"class_score": 0.00399017333984375}, "domain": "pixel"}, {"position": {"minX": 949.0, "minY": 422.75, "maxX": 1036.0, "maxY": 495.25}, "class_id": 1, "box_caption": "person 0.004", "scores": {"class_score": 0.003925323486328125}, "domain": "pixel"}, {"position": {"minX": 243.75, "minY": 161.5, "maxX": 291.25, "maxY": 274.75}, "class_id": 1, "box_caption": "person 0.004", "scores": {"class_score": 0.0039215087890625}, "domain": "pixel"}, {"position": {"minX": 837.0, "minY": 427.25, "maxX": 855.0, "maxY": 450.25}, "class_id": 0, "box_caption": "car 0.004", "scores": {"class_score": 0.0039005279541015625}, "domain": "pixel"}, {"position": {"minX": 1007.5, "minY": 410.5, "maxX": 1188.0, "maxY": 535.5}, "class_id": 4, "box_caption": "bicycle 0.004", "scores": {"class_score": 0.0038242340087890625}, "domain": "pixel"}, {"position": {"minX": 712.0, "minY": 420.25, "maxX": 766.0, "maxY": 457.75}, "class_id": 2, "box_caption": "truck 0.004", "scores": {"class_score": 0.0037250518798828125}, "domain": "pixel"}, {"position": {"minX": 592.5, "minY": 424.75, "maxX": 740.5, "maxY": 518.5}, "class_id": 7, "box_caption": "motorcycle 0.004", "scores": {"class_score": 0.0037212371826171875}, "domain": "pixel"}, {"position": {"minX": 1065.0, "minY": 410.0, "maxX": 1089.0, "maxY": 419.5}, "class_id": 0, "box_caption": "car 0.004", "scores": {"class_score": 0.0036468505859375}, "domain": "pixel"}, {"position": {"minX": 824.5, "minY": 415.75, "maxX": 837.5, "maxY": 427.25}, "class_id": 1, "box_caption": "person 0.004", "scores": {"class_score": 0.003627777099609375}, "domain": "pixel"}, {"position": {"minX": 592.5, "minY": 424.75, "maxX": 740.5, "maxY": 518.5}, "class_id": 5, "box_caption": "rider 0.004", "scores": {"class_score": 0.003551483154296875}, "domain": "pixel"}, {"position": {"minX": 783.5, "minY": 397.25, "maxX": 827.5, "maxY": 438.25}, "class_id": 0, "box_caption": "car 0.004", "scores": {"class_score": 0.0035419464111328125}, "domain": "pixel"}, {"position": {"minX": 949.0, "minY": 422.75, "maxX": 1036.0, "maxY": 495.25}, "class_id": 2, "box_caption": "truck 0.004", "scores": {"class_score": 0.00353240966796875}, "domain": "pixel"}, {"position": {"minX": 766.0, "minY": 408.5, "maxX": 797.0, "maxY": 432.5}, "class_id": 0, "box_caption": "car 0.004", "scores": {"class_score": 0.003528594970703125}, "domain": "pixel"}, {"position": {"minX": 885.5, "minY": 424.5, "maxX": 937.5, "maxY": 462.5}, "class_id": 3, "box_caption": "bus 0.004", "scores": {"class_score": 0.0035076141357421875}, "domain": "pixel"}, {"position": {"minX": 852.5, "minY": 424.75, "maxX": 894.5, "maxY": 460.25}, "class_id": 4, "box_caption": "bicycle 0.003", "scores": {"class_score": 0.0033893585205078125}, "domain": "pixel"}, {"position": {"minX": 864.0, "minY": 423.0, "maxX": 899.0, "maxY": 450.5}, "class_id": 2, "box_caption": "truck 0.003", "scores": {"class_score": 0.003376007080078125}, "domain": "pixel"}, {"position": {"minX": 1008.0, "minY": 410.5, "maxX": 1188.0, "maxY": 535.5}, "class_id": 7, "box_caption": "motorcycle 0.003", "scores": {"class_score": 0.003353118896484375}, "domain": "pixel"}, {"position": {"minX": 710.0, "minY": 422.75, "maxX": 733.0, "maxY": 437.75}, "class_id": 0, "box_caption": "car 0.003", "scores": {"class_score": 0.003314971923828125}, "domain": "pixel"}, {"position": {"minX": 592.5, "minY": 424.75, "maxX": 740.5, "maxY": 518.5}, "class_id": 6, "box_caption": "trailer 0.003", "scores": {"class_score": 0.0032863616943359375}, "domain": "pixel"}, {"position": {"minX": 1008.0, "minY": 410.5, "maxX": 1188.0, "maxY": 535.5}, "class_id": 5, "box_caption": "rider 0.003", "scores": {"class_score": 0.0032501220703125}, "domain": "pixel"}, {"position": {"minX": 1007.5, "minY": 410.5, "maxX": 1188.0, "maxY": 535.5}, "class_id": 9, "box_caption": "train 0.003", "scores": {"class_score": 0.0032100677490234375}, "domain": "pixel"}, {"position": {"minX": 1007.5, "minY": 410.5, "maxX": 1188.0, "maxY": 535.5}, "class_id": 6, "box_caption": "trailer 0.003", "scores": {"class_score": 0.00319671630859375}, "domain": "pixel"}, {"position": {"minX": 949.0, "minY": 422.75, "maxX": 1036.0, "maxY": 495.25}, "class_id": 3, "box_caption": "bus 0.003", "scores": {"class_score": 0.003192901611328125}, "domain": "pixel"}, {"position": {"minX": 695.5, "minY": 373.25, "maxX": 703.5, "maxY": 407.25}, "class_id": 0, "box_caption": "car 0.003", "scores": {"class_score": 0.00316619873046875}, "domain": "pixel"}, {"position": {"minX": 713.0, "minY": 419.5, "maxX": 766.0, "maxY": 459.5}, "class_id": 3, "box_caption": "bus 0.003", "scores": {"class_score": 0.0031642913818359375}, "domain": "pixel"}, {"position": {"minX": 592.5, "minY": 424.75, "maxX": 740.5, "maxY": 518.5}, "class_id": 9, "box_caption": "train 0.003", "scores": {"class_score": 0.00313568115234375}, "domain": "pixel"}, {"position": {"minX": 903.5, "minY": 429.25, "maxX": 940.5, "maxY": 464.25}, "class_id": 0, "box_caption": "car 0.003", "scores": {"class_score": 0.00311279296875}, "domain": "pixel"}, {"position": {"minX": 822.5, "minY": 417.5, "maxX": 840.5, "maxY": 446.0}, "class_id": 0, "box_caption": "car 0.003", "scores": {"class_score": 0.0030956268310546875}, "domain": "pixel"}, {"position": {"minX": 660.0, "minY": 373.0, "maxX": 686.0, "maxY": 432.0}, "class_id": 3, "box_caption": "bus 0.003", "scores": {"class_score": 0.0030727386474609375}, "domain": "pixel"}, {"position": {"minX": 886.5, "minY": 425.0, "maxX": 937.5, "maxY": 462.0}, "class_id": 8, "box_caption": "caravan 0.003", "scores": {"class_score": 0.0030670166015625}, "domain": "pixel"}, {"position": {"minX": 948.5, "minY": 423.5, "maxX": 1034.0, "maxY": 494.5}, "class_id": 8, "box_caption": "caravan 0.003", "scores": {"class_score": 0.0030651092529296875}, "domain": "pixel"}, {"position": {"minX": 1007.5, "minY": 410.5, "maxX": 1188.0, "maxY": 535.5}, "class_id": 1, "box_caption": "person 0.003", "scores": {"class_score": 0.0030517578125}, "domain": "pixel"}, {"position": {"minX": 832.5, "minY": 420.25, "maxX": 844.5, "maxY": 441.75}, "class_id": 1, "box_caption": "person 0.003", "scores": {"class_score": 0.0030460357666015625}, "domain": "pixel"}, {"position": {"minX": 921.5, "minY": 423.75, "maxX": 980.5, "maxY": 473.75}, "class_id": 2, "box_caption": "truck 0.003", "scores": {"class_score": 0.00302886962890625}, "domain": "pixel"}, {"position": {"minX": 836.5, "minY": 411.5, "maxX": 865.5, "maxY": 427.5}, "class_id": 0, "box_caption": "car 0.003", "scores": {"class_score": 0.0030269622802734375}, "domain": "pixel"}, {"position": {"minX": 851.5, "minY": 425.5, "maxX": 885.5, "maxY": 456.0}, "class_id": 7, "box_caption": "motorcycle 0.003", "scores": {"class_score": 0.003002166748046875}, "domain": "pixel"}, {"position": {"minX": 851.0, "minY": 419.5, "maxX": 888.0, "maxY": 447.5}, "class_id": 3, "box_caption": "bus 0.003", "scores": {"class_score": 0.0029773712158203125}, "domain": "pixel"}, {"position": {"minX": 848.0, "minY": 432.5, "maxX": 874.0, "maxY": 458.5}, "class_id": 0, "box_caption": "car 0.003", "scores": {"class_score": 0.00287628173828125}, "domain": "pixel"}, {"position": {"minX": 775.0, "minY": 411.0, "maxX": 799.0, "maxY": 434.5}, "class_id": 1, "box_caption": "person 0.003", "scores": {"class_score": 0.0028629302978515625}, "domain": "pixel"}, {"position": {"minX": 864.0, "minY": 423.0, "maxX": 899.0, "maxY": 450.5}, "class_id": 3, "box_caption": "bus 0.003", "scores": {"class_score": 0.002849578857421875}, "domain": "pixel"}, {"position": {"minX": 795.0, "minY": 421.75, "maxX": 837.0, "maxY": 450.25}, "class_id": 8, "box_caption": "caravan 0.003", "scores": {"class_score": 0.002834320068359375}, "domain": "pixel"}, {"position": {"minX": 708.0, "minY": 424.25, "maxX": 723.0, "maxY": 440.25}, "class_id": 0, "box_caption": "car 0.003", "scores": {"class_score": 0.00281524658203125}, "domain": "pixel"}, {"position": {"minX": 783.5, "minY": 397.25, "maxX": 827.5, "maxY": 438.25}, "class_id": 2, "box_caption": "truck 0.003", "scores": {"class_score": 0.0028057098388671875}, "domain": "pixel"}, {"position": {"minX": 833.5, "minY": 414.75, "maxX": 859.5, "maxY": 436.25}, "class_id": 1, "box_caption": "person 0.003", "scores": {"class_score": 0.0027637481689453125}, "domain": "pixel"}, {"position": {"minX": 711.0, "minY": 422.5, "maxX": 740.0, "maxY": 445.0}, "class_id": 0, "box_caption": "car 0.003", "scores": {"class_score": 0.002758026123046875}, "domain": "pixel"}, {"position": {"minX": 929.0, "minY": 423.75, "maxX": 1014.0, "maxY": 479.75}, "class_id": 0, "box_caption": "car 0.003", "scores": {"class_score": 0.00274658203125}, "domain": "pixel"}, {"position": {"minX": 713.0, "minY": 419.5, "maxX": 766.0, "maxY": 459.5}, "class_id": 8, "box_caption": "caravan 0.003", "scores": {"class_score": 0.0027294158935546875}, "domain": "pixel"}, {"position": {"minX": 775.5, "minY": 417.0, "maxX": 797.5, "maxY": 442.0}, "class_id": 8, "box_caption": "caravan 0.003", "scores": {"class_score": 0.002719879150390625}, "domain": "pixel"}, {"position": {"minX": 921.0, "minY": 423.75, "maxX": 980.0, "maxY": 473.75}, "class_id": 3, "box_caption": "bus 0.003", "scores": {"class_score": 0.002716064453125}, "domain": "pixel"}, {"position": {"minX": 796.0, "minY": 422.0, "maxX": 836.0, "maxY": 450.5}, "class_id": 4, "box_caption": "bicycle 0.003", "scores": {"class_score": 0.0027027130126953125}, "domain": "pixel"}, {"position": {"minX": 885.5, "minY": 424.5, "maxX": 937.5, "maxY": 462.5}, "class_id": 5, "box_caption": "rider 0.003", "scores": {"class_score": 0.0027027130126953125}, "domain": "pixel"}, {"position": {"minX": 1007.5, "minY": 414.5, "maxX": 1021.5, "maxY": 429.0}, "class_id": 1, "box_caption": "person 0.003", "scores": {"class_score": 0.00266265869140625}, "domain": "pixel"}, {"position": {"minX": 921.5, "minY": 423.75, "maxX": 980.5, "maxY": 473.75}, "class_id": 8, "box_caption": "caravan 0.003", "scores": {"class_score": 0.0026531219482421875}, "domain": "pixel"}, {"position": {"minX": 949.0, "minY": 423.25, "maxX": 1035.0, "maxY": 495.75}, "class_id": 7, "box_caption": "motorcycle 0.003", "scores": {"class_score": 0.00263214111328125}, "domain": "pixel"}, {"position": {"minX": 763.5, "minY": 410.5, "maxX": 784.5, "maxY": 424.0}, "class_id": 0, "box_caption": "car 0.003", "scores": {"class_score": 0.002620697021484375}, "domain": "pixel"}, {"position": {"minX": 885.5, "minY": 424.5, "maxX": 937.5, "maxY": 462.5}, "class_id": 1, "box_caption": "person 0.003", "scores": {"class_score": 0.0026111602783203125}, "domain": "pixel"}, {"position": {"minX": 92.75, "minY": 460.5, "maxX": 813.0, "maxY": 720.5}, "class_id": 1, "box_caption": "person 0.003", "scores": {"class_score": 0.0026111602783203125}, "domain": "pixel"}, {"position": {"minX": 747.5, "minY": 411.75, "maxX": 786.5, "maxY": 450.25}, "class_id": 3, "box_caption": "bus 0.003", "scores": {"class_score": 0.0025806427001953125}, "domain": "pixel"}, {"position": {"minX": 831.5, "minY": 417.0, "maxX": 846.5, "maxY": 436.0}, "class_id": 2, "box_caption": "truck 0.003", "scores": {"class_score": 0.002574920654296875}, "domain": "pixel"}, {"position": {"minX": 667.5, "minY": 369.75, "maxX": 699.5, "maxY": 428.75}, "class_id": 1, "box_caption": "person 0.003", "scores": {"class_score": 0.002574920654296875}, "domain": "pixel"}, {"position": {"minX": 832.0, "minY": 413.75, "maxX": 861.0, "maxY": 435.25}, "class_id": 3, "box_caption": "bus 0.002", "scores": {"class_score": 0.002498626708984375}, "domain": "pixel"}, {"position": {"minX": 909.5, "minY": 420.5, "maxX": 967.5, "maxY": 448.5}, "class_id": 0, "box_caption": "car 0.002", "scores": {"class_score": 0.0024852752685546875}, "domain": "pixel"}, {"position": {"minX": 835.5, "minY": 411.5, "maxX": 870.5, "maxY": 434.0}, "class_id": 3, "box_caption": "bus 0.002", "scores": {"class_score": 0.00247955322265625}, "domain": "pixel"}, {"position": {"minX": 948.0, "minY": 423.0, "maxX": 1036.0, "maxY": 495.0}, "class_id": 4, "box_caption": "bicycle 0.002", "scores": {"class_score": 0.0024509429931640625}, "domain": "pixel"}, {"position": {"minX": 885.5, "minY": 424.5, "maxX": 937.5, "maxY": 462.5}, "class_id": 9, "box_caption": "train 0.002", "scores": {"class_score": 0.0024433135986328125}, "domain": "pixel"}, {"position": {"minX": 885.5, "minY": 424.5, "maxX": 937.5, "maxY": 462.5}, "class_id": 7, "box_caption": "motorcycle 0.002", "scores": {"class_score": 0.00243377685546875}, "domain": "pixel"}, {"position": {"minX": 855.5, "minY": 421.5, "maxX": 897.5, "maxY": 454.5}, "class_id": 7, "box_caption": "motorcycle 0.002", "scores": {"class_score": 0.0024242401123046875}, "domain": "pixel"}, {"position": {"minX": 749.5, "minY": 412.75, "maxX": 784.5, "maxY": 452.25}, "class_id": 8, "box_caption": "caravan 0.002", "scores": {"class_score": 0.00241851806640625}, "domain": "pixel"}, {"position": {"minX": 773.5, "minY": 411.25, "maxX": 796.5, "maxY": 431.25}, "class_id": 2, "box_caption": "truck 0.002", "scores": {"class_score": 0.0024166107177734375}, "domain": "pixel"}, {"position": {"minX": 949.0, "minY": 423.25, "maxX": 1035.0, "maxY": 495.75}, "class_id": 5, "box_caption": "rider 0.002", "scores": {"class_score": 0.002414703369140625}, "domain": "pixel"}, {"position": {"minX": 745.5, "minY": 412.25, "maxX": 767.5, "maxY": 424.25}, "class_id": 0, "box_caption": "car 0.002", "scores": {"class_score": 0.0024089813232421875}, "domain": "pixel"}, {"position": {"minX": 853.5, "minY": 413.75, "maxX": 881.5, "maxY": 431.75}, "class_id": 3, "box_caption": "bus 0.002", "scores": {"class_score": 0.0024051666259765625}, "domain": "pixel"}, {"position": {"minX": 750.0, "minY": 423.75, "maxX": 770.0, "maxY": 457.75}, "class_id": 1, "box_caption": "person 0.002", "scores": {"class_score": 0.0024013519287109375}, "domain": "pixel"}, {"position": {"minX": 885.5, "minY": 424.5, "maxX": 937.5, "maxY": 462.5}, "class_id": 4, "box_caption": "bicycle 0.002", "scores": {"class_score": 0.002376556396484375}, "domain": "pixel"}, {"position": {"minX": 713.0, "minY": 419.5, "maxX": 766.0, "maxY": 459.5}, "class_id": 5, "box_caption": "rider 0.002", "scores": {"class_score": 0.0023365020751953125}, "domain": "pixel"}, {"position": {"minX": 713.0, "minY": 419.5, "maxX": 766.0, "maxY": 459.5}, "class_id": 9, "box_caption": "train 0.002", "scores": {"class_score": 0.0023365020751953125}, "domain": "pixel"}, {"position": {"minX": 816.0, "minY": 405.75, "maxX": 875.0, "maxY": 444.25}, "class_id": 0, "box_caption": "car 0.002", "scores": {"class_score": 0.0023345947265625}, "domain": "pixel"}, {"position": {"minX": 885.5, "minY": 424.5, "maxX": 937.5, "maxY": 462.5}, "class_id": 6, "box_caption": "trailer 0.002", "scores": {"class_score": 0.002323150634765625}, "domain": "pixel"}, {"position": {"minX": 775.0, "minY": 411.0, "maxX": 799.0, "maxY": 435.0}, "class_id": 8, "box_caption": "caravan 0.002", "scores": {"class_score": 0.00229644775390625}, "domain": "pixel"}, {"position": {"minX": 713.0, "minY": 419.5, "maxX": 766.0, "maxY": 459.5}, "class_id": 7, "box_caption": "motorcycle 0.002", "scores": {"class_score": 0.0022735595703125}, "domain": "pixel"}, {"position": {"minX": 713.0, "minY": 419.5, "maxX": 766.0, "maxY": 459.5}, "class_id": 4, "box_caption": "bicycle 0.002", "scores": {"class_score": 0.002246856689453125}, "domain": "pixel"}, {"position": {"minX": 796.0, "minY": 422.0, "maxX": 836.0, "maxY": 450.5}, "class_id": 7, "box_caption": "motorcycle 0.002", "scores": {"class_score": 0.0022411346435546875}, "domain": "pixel"}, {"position": {"minX": 921.5, "minY": 423.5, "maxX": 980.5, "maxY": 474.0}, "class_id": 7, "box_caption": "motorcycle 0.002", "scores": {"class_score": 0.002223968505859375}, "domain": "pixel"}, {"position": {"minX": 949.0, "minY": 422.75, "maxX": 1036.0, "maxY": 495.25}, "class_id": 6, "box_caption": "trailer 0.002", "scores": {"class_score": 0.002223968505859375}, "domain": "pixel"}, {"position": {"minX": 948.0, "minY": 423.0, "maxX": 1036.0, "maxY": 495.0}, "class_id": 9, "box_caption": "train 0.002", "scores": {"class_score": 0.002216339111328125}, "domain": "pixel"}, {"position": {"minX": 712.5, "minY": 419.0, "maxX": 766.5, "maxY": 460.0}, "class_id": 1, "box_caption": "person 0.002", "scores": {"class_score": 0.0022068023681640625}, "domain": "pixel"}, {"position": {"minX": 921.0, "minY": 423.25, "maxX": 944.0, "maxY": 439.75}, "class_id": 0, "box_caption": "car 0.002", "scores": {"class_score": 0.002197265625}, "domain": "pixel"}, {"position": {"minX": 921.5, "minY": 423.5, "maxX": 980.5, "maxY": 474.0}, "class_id": 5, "box_caption": "rider 0.002", "scores": {"class_score": 0.0021724700927734375}, "domain": "pixel"}, {"position": {"minX": 713.0, "minY": 419.5, "maxX": 766.0, "maxY": 459.5}, "class_id": 6, "box_caption": "trailer 0.002", "scores": {"class_score": 0.00213623046875}, "domain": "pixel"}, {"position": {"minX": 787.0, "minY": 404.5, "maxX": 821.0, "maxY": 429.0}, "class_id": 8, "box_caption": "caravan 0.002", "scores": {"class_score": 0.0021209716796875}, "domain": "pixel"}, {"position": {"minX": 749.5, "minY": 412.75, "maxX": 784.5, "maxY": 452.25}, "class_id": 5, "box_caption": "rider 0.002", "scores": {"class_score": 0.002101898193359375}, "domain": "pixel"}, {"position": {"minX": 775.0, "minY": 415.0, "maxX": 797.0, "maxY": 443.0}, "class_id": 1, "box_caption": "person 0.002", "scores": {"class_score": 0.002094268798828125}, "domain": "pixel"}, {"position": {"minX": 921.5, "minY": 423.5, "maxX": 980.5, "maxY": 474.0}, "class_id": 9, "box_caption": "train 0.002", "scores": {"class_score": 0.0020885467529296875}, "domain": "pixel"}, {"position": {"minX": 332.0, "minY": 454.0, "maxX": 796.0, "maxY": 617.0}, "class_id": 1, "box_caption": "person 0.002", "scores": {"class_score": 0.0020542144775390625}, "domain": "pixel"}, {"position": {"minX": 880.5, "minY": 415.0, "maxX": 898.5, "maxY": 429.0}, "class_id": 0, "box_caption": "car 0.002", "scores": {"class_score": 0.0020389556884765625}, "domain": "pixel"}, {"position": {"minX": 750.0, "minY": 411.25, "maxX": 779.0, "maxY": 423.25}, "class_id": 0, "box_caption": "car 0.002", "scores": {"class_score": 0.0020351409912109375}, "domain": "pixel"}, {"position": {"minX": 794.5, "minY": 421.75, "maxX": 836.5, "maxY": 450.25}, "class_id": 1, "box_caption": "person 0.002", "scores": {"class_score": 0.0020236968994140625}, "domain": "pixel"}, {"position": {"minX": 776.5, "minY": 407.75, "maxX": 811.5, "maxY": 435.25}, "class_id": 8, "box_caption": "caravan 0.002", "scores": {"class_score": 0.00200653076171875}, "domain": "pixel"}, {"position": {"minX": 772.5, "minY": 429.25, "maxX": 788.5, "maxY": 450.75}, "class_id": 0, "box_caption": "car 0.002", "scores": {"class_score": 0.00199127197265625}, "domain": "pixel"}, {"position": {"minX": 749.5, "minY": 412.75, "maxX": 784.5, "maxY": 452.25}, "class_id": 7, "box_caption": "motorcycle 0.002", "scores": {"class_score": 0.0019893646240234375}, "domain": "pixel"}, {"position": {"minX": 921.5, "minY": 423.75, "maxX": 980.5, "maxY": 473.75}, "class_id": 4, "box_caption": "bicycle 0.002", "scores": {"class_score": 0.0019893646240234375}, "domain": "pixel"}, {"position": {"minX": 777.0, "minY": 410.0, "maxX": 800.0, "maxY": 428.5}, "class_id": 3, "box_caption": "bus 0.002", "scores": {"class_score": 0.001987457275390625}, "domain": "pixel"}, {"position": {"minX": 769.5, "minY": 403.75, "maxX": 810.5, "maxY": 445.75}, "class_id": 2, "box_caption": "truck 0.002", "scores": {"class_score": 0.00196075439453125}, "domain": "pixel"}, {"position": {"minX": 795.0, "minY": 422.5, "maxX": 836.0, "maxY": 450.5}, "class_id": 5, "box_caption": "rider 0.002", "scores": {"class_score": 0.0019521713256835938}, "domain": "pixel"}, {"position": {"minX": 479.25, "minY": 449.75, "maxX": 502.75, "maxY": 478.75}, "class_id": 1, "box_caption": "person 0.002", "scores": {"class_score": 0.001941680908203125}, "domain": "pixel"}, {"position": {"minX": 749.5, "minY": 412.75, "maxX": 784.5, "maxY": 452.25}, "class_id": 4, "box_caption": "bicycle 0.002", "scores": {"class_score": 0.0019292831420898438}, "domain": "pixel"}, {"position": {"minX": 778.0, "minY": 409.75, "maxX": 808.0, "maxY": 431.75}, "class_id": 1, "box_caption": "person 0.002", "scores": {"class_score": 0.0019245147705078125}, "domain": "pixel"}, {"position": {"minX": 860.0, "minY": 403.25, "maxX": 881.0, "maxY": 416.75}, "class_id": 0, "box_caption": "car 0.002", "scores": {"class_score": 0.0019235610961914062}, "domain": "pixel"}, {"position": {"minX": 878.5, "minY": 432.75, "maxX": 900.5, "maxY": 461.25}, "class_id": 0, "box_caption": "car 0.002", "scores": {"class_score": 0.0018949508666992188}, "domain": "pixel"}, {"position": {"minX": 854.0, "minY": 424.25, "maxX": 896.0, "maxY": 458.75}, "class_id": 2, "box_caption": "truck 0.002", "scores": {"class_score": 0.0018949508666992188}, "domain": "pixel"}, {"position": {"minX": 921.0, "minY": 423.75, "maxX": 980.0, "maxY": 473.75}, "class_id": 6, "box_caption": "trailer 0.002", "scores": {"class_score": 0.0018901824951171875}, "domain": "pixel"}, {"position": {"minX": 853.0, "minY": 411.5, "maxX": 882.0, "maxY": 434.0}, "class_id": 2, "box_caption": "truck 0.002", "scores": {"class_score": 0.0018854141235351562}, "domain": "pixel"}, {"position": {"minX": 665.0, "minY": 372.75, "maxX": 699.0, "maxY": 431.75}, "class_id": 4, "box_caption": "bicycle 0.002", "scores": {"class_score": 0.001857757568359375}, "domain": "pixel"}, {"position": {"minX": 795.0, "minY": 422.5, "maxX": 836.0, "maxY": 450.5}, "class_id": 9, "box_caption": "train 0.002", "scores": {"class_score": 0.0018405914306640625}, "domain": "pixel"}, {"position": {"minX": 883.5, "minY": 421.75, "maxX": 916.5, "maxY": 435.25}, "class_id": 0, "box_caption": "car 0.002", "scores": {"class_score": 0.0018281936645507812}, "domain": "pixel"}, {"position": {"minX": 831.5, "minY": 417.0, "maxX": 846.5, "maxY": 436.0}, "class_id": 3, "box_caption": "bus 0.002", "scores": {"class_score": 0.0018186569213867188}, "domain": "pixel"}, {"position": {"minX": 952.5, "minY": 426.25, "maxX": 990.5, "maxY": 475.75}, "class_id": 0, "box_caption": "car 0.002", "scores": {"class_score": 0.0018110275268554688}, "domain": "pixel"}, {"position": {"minX": 851.5, "minY": 425.5, "maxX": 885.5, "maxY": 456.0}, "class_id": 1, "box_caption": "person 0.002", "scores": {"class_score": 0.0017986297607421875}, "domain": "pixel"}, {"position": {"minX": 842.5, "minY": 415.25, "maxX": 875.5, "maxY": 434.75}, "class_id": 3, "box_caption": "bus 0.002", "scores": {"class_score": 0.0017290115356445312}, "domain": "pixel"}, {"position": {"minX": 859.5, "minY": 405.5, "maxX": 882.5, "maxY": 425.0}, "class_id": 8, "box_caption": "caravan 0.002", "scores": {"class_score": 0.0017242431640625}, "domain": "pixel"}, {"position": {"minX": 921.5, "minY": 423.75, "maxX": 980.5, "maxY": 473.75}, "class_id": 1, "box_caption": "person 0.002", "scores": {"class_score": 0.0017156600952148438}, "domain": "pixel"}, {"position": {"minX": 843.0, "minY": 416.5, "maxX": 878.0, "maxY": 445.5}, "class_id": 2, "box_caption": "truck 0.002", "scores": {"class_score": 0.0016994476318359375}, "domain": "pixel"}, {"position": {"minX": 871.5, "minY": 408.25, "maxX": 893.5, "maxY": 424.25}, "class_id": 3, "box_caption": "bus 0.002", "scores": {"class_score": 0.0016965866088867188}, "domain": "pixel"}, {"position": {"minX": 763.0, "minY": 409.0, "maxX": 823.0, "maxY": 448.0}, "class_id": 0, "box_caption": "car 0.002", "scores": {"class_score": 0.0016317367553710938}, "domain": "pixel"}, {"position": {"minX": 663.5, "minY": 372.25, "maxX": 681.5, "maxY": 423.75}, "class_id": 3, "box_caption": "bus 0.002", "scores": {"class_score": 0.0016260147094726562}, "domain": "pixel"}, {"position": {"minX": 833.0, "minY": 428.0, "maxX": 844.0, "maxY": 449.0}, "class_id": 0, "box_caption": "car 0.002", "scores": {"class_score": 0.0016164779663085938}, "domain": "pixel"}, {"position": {"minX": 858.5, "minY": 406.75, "maxX": 888.5, "maxY": 425.75}, "class_id": 1, "box_caption": "person 0.002", "scores": {"class_score": 0.001613616943359375}, "domain": "pixel"}, {"position": {"minX": 795.0, "minY": 422.5, "maxX": 836.0, "maxY": 450.5}, "class_id": 6, "box_caption": "trailer 0.002", "scores": {"class_score": 0.001613616943359375}, "domain": "pixel"}, {"position": {"minX": 795.0, "minY": 405.5, "maxX": 824.0, "maxY": 425.5}, "class_id": 8, "box_caption": "caravan 0.002", "scores": {"class_score": 0.0016126632690429688}, "domain": "pixel"}, {"position": {"minX": 749.5, "minY": 412.75, "maxX": 784.5, "maxY": 452.25}, "class_id": 9, "box_caption": "train 0.002", "scores": {"class_score": 0.001575469970703125}, "domain": "pixel"}, {"position": {"minX": 889.0, "minY": 417.0, "maxX": 940.0, "maxY": 451.5}, "class_id": 0, "box_caption": "car 0.002", "scores": {"class_score": 0.0015716552734375}, "domain": "pixel"}, {"position": {"minX": 456.25, "minY": 446.5, "maxX": 481.75, "maxY": 470.0}, "class_id": 0, "box_caption": "car 0.002", "scores": {"class_score": 0.0015468597412109375}, "domain": "pixel"}, {"position": {"minX": 832.0, "minY": 413.75, "maxX": 861.0, "maxY": 435.25}, "class_id": 8, "box_caption": "caravan 0.002", "scores": {"class_score": 0.001537322998046875}, "domain": "pixel"}, {"position": {"minX": 945.5, "minY": 424.75, "maxX": 981.5, "maxY": 439.25}, "class_id": 0, "box_caption": "car 0.001", "scores": {"class_score": 0.0014934539794921875}, "domain": "pixel"}, {"position": {"minX": 663.5, "minY": 372.25, "maxX": 681.5, "maxY": 423.75}, "class_id": 0, "box_caption": "car 0.001", "scores": {"class_score": 0.0014829635620117188}, "domain": "pixel"}, {"position": {"minX": 794.5, "minY": 405.5, "maxX": 824.5, "maxY": 427.5}, "class_id": 1, "box_caption": "person 0.001", "scores": {"class_score": 0.0014705657958984375}, "domain": "pixel"}, {"position": {"minX": 680.0, "minY": 371.75, "maxX": 702.0, "maxY": 410.25}, "class_id": 0, "box_caption": "car 0.001", "scores": {"class_score": 0.0014677047729492188}, "domain": "pixel"}, {"position": {"minX": 787.0, "minY": 391.75, "maxX": 841.0, "maxY": 435.25}, "class_id": 0, "box_caption": "car 0.001", "scores": {"class_score": 0.0014638900756835938}, "domain": "pixel"}, {"position": {"minX": 954.5, "minY": 424.5, "maxX": 985.5, "maxY": 444.5}, "class_id": 0, "box_caption": "car 0.001", "scores": {"class_score": 0.00145721435546875}, "domain": "pixel"}, {"position": {"minX": 449.75, "minY": 443.75, "maxX": 488.75, "maxY": 472.25}, "class_id": 0, "box_caption": "car 0.001", "scores": {"class_score": 0.0014476776123046875}, "domain": "pixel"}, {"position": {"minX": 441.75, "minY": 409.5, "maxX": 558.5, "maxY": 466.5}, "class_id": 0, "box_caption": "car 0.001", "scores": {"class_score": 0.001438140869140625}, "domain": "pixel"}, {"position": {"minX": 766.0, "minY": 412.25, "maxX": 782.0, "maxY": 422.75}, "class_id": 1, "box_caption": "person 0.001", "scores": {"class_score": 0.00142669677734375}, "domain": "pixel"}, {"position": {"minX": 775.5, "minY": 417.0, "maxX": 797.5, "maxY": 442.0}, "class_id": 5, "box_caption": "rider 0.001", "scores": {"class_score": 0.0014095306396484375}, "domain": "pixel"}, {"position": {"minX": 936.5, "minY": 422.25, "maxX": 1003.5, "maxY": 466.75}, "class_id": 0, "box_caption": "car 0.001", "scores": {"class_score": 0.0014066696166992188}, "domain": "pixel"}, {"position": {"minX": 1030.0, "minY": 412.25, "maxX": 1042.0, "maxY": 428.75}, "class_id": 1, "box_caption": "person 0.001", "scores": {"class_score": 0.0014047622680664062}, "domain": "pixel"}, {"position": {"minX": 875.0, "minY": 420.75, "maxX": 924.0, "maxY": 437.75}, "class_id": 0, "box_caption": "car 0.001", "scores": {"class_score": 0.0014009475708007812}, "domain": "pixel"}, {"position": {"minX": 842.5, "minY": 415.25, "maxX": 875.5, "maxY": 434.75}, "class_id": 2, "box_caption": "truck 0.001", "scores": {"class_score": 0.0013704299926757812}, "domain": "pixel"}, {"position": {"minX": 846.5, "minY": 416.5, "maxX": 874.5, "maxY": 440.5}, "class_id": 1, "box_caption": "person 0.001", "scores": {"class_score": 0.0013704299926757812}, "domain": "pixel"}, {"position": {"minX": 862.5, "minY": 422.5, "maxX": 899.5, "maxY": 449.0}, "class_id": 1, "box_caption": "person 0.001", "scores": {"class_score": 0.0013704299926757812}, "domain": "pixel"}, {"position": {"minX": 798.5, "minY": 404.75, "maxX": 839.5, "maxY": 431.25}, "class_id": 2, "box_caption": "truck 0.001", "scores": {"class_score": 0.0013484954833984375}, "domain": "pixel"}, {"position": {"minX": 543.0, "minY": 438.0, "maxX": 562.0, "maxY": 465.5}, "class_id": 0, "box_caption": "car 0.001", "scores": {"class_score": 0.0013475418090820312}, "domain": "pixel"}, {"position": {"minX": 935.0, "minY": 423.25, "maxX": 976.0, "maxY": 442.25}, "class_id": 0, "box_caption": "car 0.001", "scores": {"class_score": 0.0013446807861328125}, "domain": "pixel"}, {"position": {"minX": 745.5, "minY": 411.5, "maxX": 785.5, "maxY": 450.0}, "class_id": 6, "box_caption": "trailer 0.001", "scores": {"class_score": 0.0013446807861328125}, "domain": "pixel"}, {"position": {"minX": 445.25, "minY": 430.75, "maxX": 506.75, "maxY": 475.25}, "class_id": 0, "box_caption": "car 0.001", "scores": {"class_score": 0.0013322830200195312}, "domain": "pixel"}, {"position": {"minX": 712.5, "minY": 426.5, "maxX": 744.5, "maxY": 456.5}, "class_id": 0, "box_caption": "car 0.001", "scores": {"class_score": 0.0013256072998046875}, "domain": "pixel"}, {"position": {"minX": 793.5, "minY": 401.25, "maxX": 825.5, "maxY": 431.75}, "class_id": 3, "box_caption": "bus 0.001", "scores": {"class_score": 0.0013217926025390625}, "domain": "pixel"}, {"position": {"minX": 454.75, "minY": 439.0, "maxX": 483.25, "maxY": 467.0}, "class_id": 0, "box_caption": "car 0.001", "scores": {"class_score": 0.00131988525390625}, "domain": "pixel"}, {"position": {"minX": 790.5, "minY": 422.0, "maxX": 811.5, "maxY": 441.5}, "class_id": 1, "box_caption": "person 0.001", "scores": {"class_score": 0.0012922286987304688}, "domain": "pixel"}, {"position": {"minX": 819.0, "minY": 405.0, "maxX": 835.0, "maxY": 426.0}, "class_id": 0, "box_caption": "car 0.001", "scores": {"class_score": 0.0012798309326171875}, "domain": "pixel"}, {"position": {"minX": 471.0, "minY": 449.0, "maxX": 508.0, "maxY": 483.5}, "class_id": 1, "box_caption": "person 0.001", "scores": {"class_score": 0.0012750625610351562}, "domain": "pixel"}, {"position": {"minX": 859.5, "minY": 422.75, "maxX": 899.5, "maxY": 453.75}, "class_id": 5, "box_caption": "rider 0.001", "scores": {"class_score": 0.0012502670288085938}, "domain": "pixel"}, {"position": {"minX": 728.0, "minY": 414.5, "maxX": 755.0, "maxY": 426.5}, "class_id": 0, "box_caption": "car 0.001", "scores": {"class_score": 0.0012083053588867188}, "domain": "pixel"}, {"position": {"minX": 775.0, "minY": 411.0, "maxX": 799.0, "maxY": 434.5}, "class_id": 5, "box_caption": "rider 0.001", "scores": {"class_score": 0.0012044906616210938}, "domain": "pixel"}, {"position": {"minX": 785.0, "minY": 421.75, "maxX": 802.0, "maxY": 440.25}, "class_id": 1, "box_caption": "person 0.001", "scores": {"class_score": 0.0011873245239257812}, "domain": "pixel"}, {"position": {"minX": 776.0, "minY": 419.5, "maxX": 797.0, "maxY": 441.5}, "class_id": 4, "box_caption": "bicycle 0.001", "scores": {"class_score": 0.0011720657348632812}, "domain": "pixel"}, {"position": {"minX": 776.0, "minY": 419.5, "maxX": 797.0, "maxY": 441.5}, "class_id": 7, "box_caption": "motorcycle 0.001", "scores": {"class_score": 0.0011720657348632812}, "domain": "pixel"}, {"position": {"minX": 926.0, "minY": 422.5, "maxX": 953.0, "maxY": 440.0}, "class_id": 0, "box_caption": "car 0.001", "scores": {"class_score": 0.001163482666015625}, "domain": "pixel"}, {"position": {"minX": 859.5, "minY": 422.75, "maxX": 899.5, "maxY": 453.75}, "class_id": 8, "box_caption": "caravan 0.001", "scores": {"class_score": 0.00115203857421875}, "domain": "pixel"}, {"position": {"minX": 660.0, "minY": 373.0, "maxX": 686.0, "maxY": 432.0}, "class_id": 0, "box_caption": "car 0.001", "scores": {"class_score": 0.0011510848999023438}, "domain": "pixel"}, {"position": {"minX": 1068.0, "minY": 410.5, "maxX": 1096.0, "maxY": 422.0}, "class_id": 0, "box_caption": "car 0.001", "scores": {"class_score": 0.0011320114135742188}, "domain": "pixel"}, {"position": {"minX": 823.0, "minY": 408.5, "maxX": 843.0, "maxY": 427.0}, "class_id": 0, "box_caption": "car 0.001", "scores": {"class_score": 0.001129150390625}, "domain": "pixel"}, {"position": {"minX": 787.0, "minY": 391.75, "maxX": 841.0, "maxY": 435.25}, "class_id": 2, "box_caption": "truck 0.001", "scores": {"class_score": 0.0011205673217773438}, "domain": "pixel"}, {"position": {"minX": 843.0, "minY": 416.5, "maxX": 878.0, "maxY": 445.5}, "class_id": 7, "box_caption": "motorcycle 0.001", "scores": {"class_score": 0.0011119842529296875}, "domain": "pixel"}, {"position": {"minX": 850.0, "minY": 404.0, "maxX": 884.0, "maxY": 439.0}, "class_id": 2, "box_caption": "truck 0.001", "scores": {"class_score": 0.0011110305786132812}, "domain": "pixel"}, {"position": {"minX": 667.5, "minY": 369.75, "maxX": 699.5, "maxY": 428.75}, "class_id": 5, "box_caption": "rider 0.001", "scores": {"class_score": 0.0011091232299804688}, "domain": "pixel"}, {"position": {"minX": 859.5, "minY": 422.75, "maxX": 899.5, "maxY": 453.75}, "class_id": 4, "box_caption": "bicycle 0.001", "scores": {"class_score": 0.001094818115234375}, "domain": "pixel"}, {"position": {"minX": 477.5, "minY": 452.5, "maxX": 503.5, "maxY": 480.5}, "class_id": 0, "box_caption": "car 0.001", "scores": {"class_score": 0.00107574462890625}, "domain": "pixel"}, {"position": {"minX": 774.5, "minY": 414.5, "maxX": 798.5, "maxY": 442.5}, "class_id": 9, "box_caption": "train 0.001", "scores": {"class_score": 0.001068115234375}, "domain": "pixel"}, {"position": {"minX": 854.0, "minY": 425.0, "maxX": 896.0, "maxY": 458.0}, "class_id": 3, "box_caption": "bus 0.001", "scores": {"class_score": 0.0010614395141601562}, "domain": "pixel"}, {"position": {"minX": 849.5, "minY": 418.5, "maxX": 879.5, "maxY": 441.5}, "class_id": 3, "box_caption": "bus 0.001", "scores": {"class_score": 0.0010538101196289062}, "domain": "pixel"}, {"position": {"minX": 925.0, "minY": 426.75, "maxX": 955.0, "maxY": 451.25}, "class_id": 1, "box_caption": "person 0.001", "scores": {"class_score": 0.0010509490966796875}, "domain": "pixel"}, {"position": {"minX": 774.5, "minY": 414.5, "maxX": 798.5, "maxY": 442.5}, "class_id": 6, "box_caption": "trailer 0.001", "scores": {"class_score": 0.0010395050048828125}, "domain": "pixel"}, {"position": {"minX": 691.0, "minY": 376.0, "maxX": 703.0, "maxY": 429.5}, "class_id": 0, "box_caption": "car 0.001", "scores": {"class_score": 0.0010251998901367188}, "domain": "pixel"}, {"position": {"minX": 750.5, "minY": 432.0, "maxX": 767.5, "maxY": 462.5}, "class_id": 0, "box_caption": "car 0.001", "scores": {"class_score": 0.0010118484497070312}, "domain": "pixel"}, {"position": {"minX": 800.5, "minY": 408.75, "maxX": 836.5, "maxY": 426.75}, "class_id": 2, "box_caption": "truck 0.001", "scores": {"class_score": 0.0010042190551757812}, "domain": "pixel"}, {"position": {"minX": 831.5, "minY": 413.75, "maxX": 860.5, "maxY": 434.75}, "class_id": 5, "box_caption": "rider 0.001", "scores": {"class_score": 0.0010013580322265625}, "domain": "pixel"}], "class_labels": {"0": "car", "1": "person", "2": "truck", "3": "bus", "4": "bicycle", "5": "rider", "6": "trailer", "7": "motorcycle", "8": "caravan", "9": "train"}}