{"box_data": [{"position": {"minX": 470.5, "minY": 350.5, "maxX": 575.5, "maxY": 420.5}, "class_id": 0, "box_caption": "car 0.947", "scores": {"class_score": 0.94677734375}, "domain": "pixel"}, {"position": {"minX": 639.5, "minY": 338.5, "maxX": 712.5, "maxY": 410.0}, "class_id": 0, "box_caption": "car 0.932", "scores": {"class_score": 0.931640625}, "domain": "pixel"}, {"position": {"minX": 572.5, "minY": 356.5, "maxX": 630.5, "maxY": 396.5}, "class_id": 0, "box_caption": "car 0.911", "scores": {"class_score": 0.91064453125}, "domain": "pixel"}, {"position": {"minX": 716.5, "minY": 355.75, "maxX": 748.5, "maxY": 381.25}, "class_id": 0, "box_caption": "car 0.884", "scores": {"class_score": 0.8837890625}, "domain": "pixel"}, {"position": {"minX": 344.0, "minY": 349.25, "maxX": 446.0, "maxY": 387.75}, "class_id": 0, "box_caption": "car 0.863", "scores": {"class_score": 0.86328125}, "domain": "pixel"}, {"position": {"minX": 742.0, "minY": 355.25, "maxX": 763.0, "maxY": 373.75}, "class_id": 0, "box_caption": "car 0.807", "scores": {"class_score": 0.80712890625}, "domain": "pixel"}, {"position": {"minX": 764.0, "minY": 355.0, "maxX": 786.0, "maxY": 370.0}, "class_id": 0, "box_caption": "car 0.807", "scores": {"class_score": 0.806640625}, "domain": "pixel"}, {"position": {"minX": 433.5, "minY": 358.25, "maxX": 482.0, "maxY": 379.75}, "class_id": 0, "box_caption": "car 0.760", "scores": {"class_score": 0.76025390625}, "domain": "pixel"}, {"position": {"minX": 622.5, "minY": 359.5, "maxX": 643.5, "maxY": 375.0}, "class_id": 0, "box_caption": "car 0.560", "scores": {"class_score": 0.5595703125}, "domain": "pixel"}, {"position": {"minX": 160.5, "minY": 344.75, "maxX": 263.0, "maxY": 383.75}, "class_id": 0, "box_caption": "car 0.526", "scores": {"class_score": 0.52587890625}, "domain": "pixel"}, {"position": {"minX": 548.0, "minY": 353.0, "maxX": 577.0, "maxY": 375.0}, "class_id": 0, "box_caption": "car 0.526", "scores": {"class_score": 0.52587890625}, "domain": "pixel"}, {"position": {"minX": 22.75, "minY": 335.75, "maxX": 246.75, "maxY": 400.75}, "class_id": 0, "box_caption": "car 0.478", "scores": {"class_score": 0.4775390625}, "domain": "pixel"}, {"position": {"minX": 703.5, "minY": 351.5, "maxX": 723.5, "maxY": 385.0}, "class_id": 0, "box_caption": "car 0.469", "scores": {"class_score": 0.469482421875}, "domain": "pixel"}, {"position": {"minX": 702.0, "minY": 357.5, "maxX": 720.0, "maxY": 389.5}, "class_id": 0, "box_caption": "car 0.272", "scores": {"class_score": 0.272216796875}, "domain": "pixel"}, {"position": {"minX": 451.0, "minY": 354.25, "maxX": 495.5, "maxY": 371.75}, "class_id": 0, "box_caption": "car 0.260", "scores": {"class_score": 0.259765625}, "domain": "pixel"}, {"position": {"minX": 705.0, "minY": 348.0, "maxX": 729.0, "maxY": 372.0}, "class_id": 0, "box_caption": "car 0.184", "scores": {"class_score": 0.1837158203125}, "domain": "pixel"}, {"position": {"minX": 735.0, "minY": 353.5, "maxX": 759.0, "maxY": 377.0}, "class_id": 0, "box_caption": "car 0.178", "scores": {"class_score": 0.177734375}, "domain": "pixel"}, {"position": {"minX": 705.5, "minY": 364.75, "maxX": 719.5, "maxY": 387.25}, "class_id": 0, "box_caption": "car 0.170", "scores": {"class_score": 0.169677734375}, "domain": "pixel"}, {"position": {"minX": 614.5, "minY": 358.5, "maxX": 637.5, "maxY": 373.5}, "class_id": 0, "box_caption": "car 0.152", "scores": {"class_score": 0.1524658203125}, "domain": "pixel"}, {"position": {"minX": 708.0, "minY": 355.5, "maxX": 738.0, "maxY": 379.5}, "class_id": 0, "box_caption": "car 0.142", "scores": {"class_score": 0.1424560546875}, "domain": "pixel"}, {"position": {"minX": 312.0, "minY": 351.0, "maxX": 360.0, "maxY": 363.0}, "class_id": 0, "box_caption": "car 0.124", "scores": {"class_score": 0.12445068359375}, "domain": "pixel"}, {"position": {"minX": 553.0, "minY": 355.25, "maxX": 583.0, "maxY": 381.25}, "class_id": 0, "box_caption": "car 0.113", "scores": {"class_score": 0.11260986328125}, "domain": "pixel"}, {"position": {"minX": 751.5, "minY": 355.75, "maxX": 766.5, "maxY": 368.75}, "class_id": 0, "box_caption": "car 0.105", "scores": {"class_score": 0.10516357421875}, "domain": "pixel"}, {"position": {"minX": 549.0, "minY": 351.75, "maxX": 573.0, "maxY": 366.75}, "class_id": 0, "box_caption": "car 0.102", "scores": {"class_score": 0.101806640625}, "domain": "pixel"}, {"position": {"minX": 620.0, "minY": 357.25, "maxX": 646.0, "maxY": 380.25}, "class_id": 0, "box_caption": "car 0.092", "scores": {"class_score": 0.09222412109375}, "domain": "pixel"}, {"position": {"minX": 739.5, "minY": 352.75, "maxX": 767.5, "maxY": 376.25}, "class_id": 0, "box_caption": "car 0.087", "scores": {"class_score": 0.0872802734375}, "domain": "pixel"}, {"position": {"minX": 756.0, "minY": 355.75, "maxX": 768.0, "maxY": 367.25}, "class_id": 0, "box_caption": "car 0.083", "scores": {"class_score": 0.083251953125}, "domain": "pixel"}, {"position": {"minX": 293.25, "minY": 350.0, "maxX": 361.75, "maxY": 366.5}, "class_id": 0, "box_caption": "car 0.080", "scores": {"class_score": 0.07952880859375}, "domain": "pixel"}, {"position": {"minX": 457.5, "minY": 350.0, "maxX": 493.0, "maxY": 367.5}, "class_id": 0, "box_caption": "car 0.077", "scores": {"class_score": 0.07684326171875}, "domain": "pixel"}, {"position": {"minX": 467.75, "minY": 354.25, "maxX": 495.25, "maxY": 370.75}, "class_id": 0, "box_caption": "car 0.073", "scores": {"class_score": 0.07318115234375}, "domain": "pixel"}, {"position": {"minX": 611.0, "minY": 357.75, "maxX": 630.0, "maxY": 373.25}, "class_id": 0, "box_caption": "car 0.071", "scores": {"class_score": 0.071044921875}, "domain": "pixel"}, {"position": {"minX": 442.5, "minY": 353.5, "maxX": 486.0, "maxY": 373.5}, "class_id": 0, "box_caption": "car 0.067", "scores": {"class_score": 0.067138671875}, "domain": "pixel"}, {"position": {"minX": 707.0, "minY": 348.75, "maxX": 730.0, "maxY": 362.75}, "class_id": 0, "box_caption": "car 0.066", "scores": {"class_score": 0.06646728515625}, "domain": "pixel"}, {"position": {"minX": 275.5, "minY": 350.0, "maxX": 362.5, "maxY": 372.0}, "class_id": 0, "box_caption": "car 0.043", "scores": {"class_score": 0.04302978515625}, "domain": "pixel"}, {"position": {"minX": 611.5, "minY": 356.25, "maxX": 633.5, "maxY": 383.25}, "class_id": 0, "box_caption": "car 0.040", "scores": {"class_score": 0.039581298828125}, "domain": "pixel"}, {"position": {"minX": 634.0, "minY": 358.25, "maxX": 649.0, "maxY": 371.75}, "class_id": 0, "box_caption": "car 0.029", "scores": {"class_score": 0.0287017822265625}, "domain": "pixel"}, {"position": {"minX": 319.0, "minY": 349.75, "maxX": 361.5, "maxY": 359.75}, "class_id": 0, "box_caption": "car 0.026", "scores": {"class_score": 0.026214599609375}, "domain": "pixel"}, {"position": {"minX": 32.9375, "minY": 299.25, "maxX": 68.875, "maxY": 317.25}, "class_id": 0, "box_caption": "car 0.025", "scores": {"class_score": 0.0245361328125}, "domain": "pixel"}, {"position": {"minX": 554.0, "minY": 353.0, "maxX": 579.0, "maxY": 369.0}, "class_id": 0, "box_caption": "car 0.024", "scores": {"class_score": 0.024383544921875}, "domain": "pixel"}, {"position": {"minX": 613.5, "minY": 356.75, "maxX": 627.5, "maxY": 367.25}, "class_id": 0, "box_caption": "car 0.024", "scores": {"class_score": 0.02435302734375}, "domain": "pixel"}, {"position": {"minX": 460.0, "minY": 350.75, "maxX": 498.5, "maxY": 374.25}, "class_id": 0, "box_caption": "car 0.023", "scores": {"class_score": 0.02313232421875}, "domain": "pixel"}, {"position": {"minX": 617.0, "minY": 361.5, "maxX": 635.0, "maxY": 388.5}, "class_id": 0, "box_caption": "car 0.023", "scores": {"class_score": 0.022613525390625}, "domain": "pixel"}, {"position": {"minX": 695.5, "minY": 350.0, "maxX": 717.5, "maxY": 391.0}, "class_id": 0, "box_caption": "car 0.022", "scores": {"class_score": 0.022064208984375}, "domain": "pixel"}, {"position": {"minX": 22.1875, "minY": 334.25, "maxX": 173.25, "maxY": 394.25}, "class_id": 0, "box_caption": "car 0.020", "scores": {"class_score": 0.0200347900390625}, "domain": "pixel"}, {"position": {"minX": 564.0, "minY": 357.0, "maxX": 583.0, "maxY": 372.0}, "class_id": 0, "box_caption": "car 0.019", "scores": {"class_score": 0.018707275390625}, "domain": "pixel"}, {"position": {"minX": 762.0, "minY": 15.5625, "maxX": 1298.0, "maxY": 200.25}, "class_id": 9, "box_caption": "train 0.016", "scores": {"class_score": 0.0161590576171875}, "domain": "pixel"}, {"position": {"minX": 634.5, "minY": 358.25, "maxX": 650.5, "maxY": 379.75}, "class_id": 0, "box_caption": "car 0.016", "scores": {"class_score": 0.01557159423828125}, "domain": "pixel"}, {"position": {"minX": 446.0, "minY": 352.0, "maxX": 511.0, "maxY": 392.0}, "class_id": 0, "box_caption": "car 0.015", "scores": {"class_score": 0.01470184326171875}, "domain": "pixel"}, {"position": {"minX": 537.5, "minY": 351.0, "maxX": 593.5, "maxY": 385.5}, "class_id": 0, "box_caption": "car 0.014", "scores": {"class_score": 0.0142364501953125}, "domain": "pixel"}, {"position": {"minX": 22.875, "minY": 334.5, "maxX": 190.25, "maxY": 426.0}, "class_id": 0, "box_caption": "car 0.014", "scores": {"class_score": 0.01419830322265625}, "domain": "pixel"}, {"position": {"minX": 492.25, "minY": 348.75, "maxX": 537.0, "maxY": 359.25}, "class_id": 0, "box_caption": "car 0.014", "scores": {"class_score": 0.01386260986328125}, "domain": "pixel"}, {"position": {"minX": 606.0, "minY": 356.0, "maxX": 626.0, "maxY": 371.5}, "class_id": 0, "box_caption": "car 0.014", "scores": {"class_score": 0.0137481689453125}, "domain": "pixel"}, {"position": {"minX": 699.5, "minY": 347.25, "maxX": 722.5, "maxY": 371.75}, "class_id": 0, "box_caption": "car 0.013", "scores": {"class_score": 0.0127716064453125}, "domain": "pixel"}, {"position": {"minX": 101.5, "minY": 273.5, "maxX": 146.5, "maxY": 289.5}, "class_id": 0, "box_caption": "car 0.013", "scores": {"class_score": 0.0127716064453125}, "domain": "pixel"}, {"position": {"minX": 626.0, "minY": 356.5, "maxX": 646.0, "maxY": 367.0}, "class_id": 0, "box_caption": "car 0.010", "scores": {"class_score": 0.01024627685546875}, "domain": "pixel"}, {"position": {"minX": 706.5, "minY": 348.5, "maxX": 730.5, "maxY": 364.5}, "class_id": 2, "box_caption": "truck 0.010", "scores": {"class_score": 0.009796142578125}, "domain": "pixel"}, {"position": {"minX": 253.875, "minY": 347.25, "maxX": 360.0, "maxY": 377.25}, "class_id": 0, "box_caption": "car 0.009", "scores": {"class_score": 0.00942230224609375}, "domain": "pixel"}, {"position": {"minX": 466.5, "minY": 351.5, "maxX": 501.5, "maxY": 365.5}, "class_id": 0, "box_caption": "car 0.009", "scores": {"class_score": 0.0091705322265625}, "domain": "pixel"}, {"position": {"minX": 715.5, "minY": 355.0, "maxX": 748.5, "maxY": 381.5}, "class_id": 2, "box_caption": "truck 0.009", "scores": {"class_score": 0.0089263916015625}, "domain": "pixel"}, {"position": {"minX": 761.5, "minY": 351.75, "maxX": 788.5, "maxY": 375.25}, "class_id": 0, "box_caption": "car 0.009", "scores": {"class_score": 0.00852203369140625}, "domain": "pixel"}, {"position": {"minX": 624.0, "minY": 360.25, "maxX": 647.0, "maxY": 387.25}, "class_id": 0, "box_caption": "car 0.008", "scores": {"class_score": 0.0084381103515625}, "domain": "pixel"}, {"position": {"minX": 711.5, "minY": 353.0, "maxX": 759.5, "maxY": 382.0}, "class_id": 0, "box_caption": "car 0.008", "scores": {"class_score": 0.00843048095703125}, "domain": "pixel"}, {"position": {"minX": 698.5, "minY": 348.5, "maxX": 752.5, "maxY": 382.5}, "class_id": 0, "box_caption": "car 0.008", "scores": {"class_score": 0.00815582275390625}, "domain": "pixel"}, {"position": {"minX": 729.0, "minY": 352.25, "maxX": 748.0, "maxY": 364.25}, "class_id": 0, "box_caption": "car 0.008", "scores": {"class_score": 0.00804901123046875}, "domain": "pixel"}, {"position": {"minX": 727.0, "minY": 358.75, "maxX": 757.0, "maxY": 378.75}, "class_id": 0, "box_caption": "car 0.008", "scores": {"class_score": 0.0075836181640625}, "domain": "pixel"}, {"position": {"minX": 636.5, "minY": 352.5, "maxX": 649.5, "maxY": 367.5}, "class_id": 0, "box_caption": "car 0.007", "scores": {"class_score": 0.007442474365234375}, "domain": "pixel"}, {"position": {"minX": 595.5, "minY": 357.0, "maxX": 628.5, "maxY": 389.5}, "class_id": 0, "box_caption": "car 0.007", "scores": {"class_score": 0.0073699951171875}, "domain": "pixel"}, {"position": {"minX": 550.5, "minY": 358.75, "maxX": 580.5, "maxY": 388.75}, "class_id": 0, "box_caption": "car 0.007", "scores": {"class_score": 0.0072174072265625}, "domain": "pixel"}, {"position": {"minX": 437.5, "minY": 348.75, "maxX": 485.5, "maxY": 368.75}, "class_id": 0, "box_caption": "car 0.007", "scores": {"class_score": 0.007190704345703125}, "domain": "pixel"}, {"position": {"minX": 486.5, "minY": 349.5, "maxX": 530.0, "maxY": 363.0}, "class_id": 0, "box_caption": "car 0.007", "scores": {"class_score": 0.0070343017578125}, "domain": "pixel"}, {"position": {"minX": 539.5, "minY": 351.5, "maxX": 566.5, "maxY": 365.5}, "class_id": 0, "box_caption": "car 0.007", "scores": {"class_score": 0.00678253173828125}, "domain": "pixel"}, {"position": {"minX": 30.203125, "minY": 294.75, "maxX": 76.5, "maxY": 319.25}, "class_id": 0, "box_caption": "car 0.007", "scores": {"class_score": 0.006763458251953125}, "domain": "pixel"}, {"position": {"minX": 432.75, "minY": 351.0, "maxX": 494.75, "maxY": 381.0}, "class_id": 0, "box_caption": "car 0.007", "scores": {"class_score": 0.0066680908203125}, "domain": "pixel"}, {"position": {"minX": 774.5, "minY": 355.0, "maxX": 789.5, "maxY": 369.0}, "class_id": 0, "box_caption": "car 0.006", "scores": {"class_score": 0.006443023681640625}, "domain": "pixel"}, {"position": {"minX": 764.5, "minY": 353.25, "maxX": 784.5, "maxY": 365.25}, "class_id": 0, "box_caption": "car 0.006", "scores": {"class_score": 0.00604248046875}, "domain": "pixel"}, {"position": {"minX": 703.0, "minY": 349.0, "maxX": 727.0, "maxY": 384.0}, "class_id": 2, "box_caption": "truck 0.006", "scores": {"class_score": 0.00568389892578125}, "domain": "pixel"}, {"position": {"minX": 27.515625, "minY": 295.75, "maxX": 61.4375, "maxY": 316.75}, "class_id": 0, "box_caption": "car 0.006", "scores": {"class_score": 0.00554656982421875}, "domain": "pixel"}, {"position": {"minX": 581.0, "minY": 355.0, "maxX": 607.0, "maxY": 363.0}, "class_id": 0, "box_caption": "car 0.005", "scores": {"class_score": 0.004909515380859375}, "domain": "pixel"}, {"position": {"minX": 108.25, "minY": 268.0, "maxX": 154.75, "maxY": 286.5}, "class_id": 0, "box_caption": "car 0.005", "scores": {"class_score": 0.0048370361328125}, "domain": "pixel"}, {"position": {"minX": 461.0, "minY": 357.5, "maxX": 494.0, "maxY": 375.0}, "class_id": 0, "box_caption": "car 0.005", "scores": {"class_score": 0.004787445068359375}, "domain": "pixel"}, {"position": {"minX": 564.0, "minY": 359.5, "maxX": 583.0, "maxY": 378.0}, "class_id": 0, "box_caption": "car 0.005", "scores": {"class_score": 0.004756927490234375}, "domain": "pixel"}, {"position": {"minX": 537.5, "minY": 351.5, "maxX": 567.5, "maxY": 372.5}, "class_id": 0, "box_caption": "car 0.005", "scores": {"class_score": 0.00473785400390625}, "domain": "pixel"}, {"position": {"minX": 470.75, "minY": 351.25, "maxX": 575.5, "maxY": 419.75}, "class_id": 3, "box_caption": "bus 0.005", "scores": {"class_score": 0.004596710205078125}, "domain": "pixel"}, {"position": {"minX": 506.0, "minY": 348.5, "maxX": 587.0, "maxY": 396.0}, "class_id": 0, "box_caption": "car 0.004", "scores": {"class_score": 0.0044097900390625}, "domain": "pixel"}, {"position": {"minX": 640.5, "minY": 339.25, "maxX": 713.5, "maxY": 408.25}, "class_id": 2, "box_caption": "truck 0.004", "scores": {"class_score": 0.004405975341796875}, "domain": "pixel"}, {"position": {"minX": 606.5, "minY": 363.25, "maxX": 632.5, "maxY": 393.75}, "class_id": 0, "box_caption": "car 0.004", "scores": {"class_score": 0.004383087158203125}, "domain": "pixel"}, {"position": {"minX": 764.5, "minY": 355.25, "maxX": 785.5, "maxY": 369.75}, "class_id": 2, "box_caption": "truck 0.004", "scores": {"class_score": 0.0043792724609375}, "domain": "pixel"}, {"position": {"minX": 745.5, "minY": 352.25, "maxX": 767.5, "maxY": 365.25}, "class_id": 0, "box_caption": "car 0.004", "scores": {"class_score": 0.004344940185546875}, "domain": "pixel"}, {"position": {"minX": 640.5, "minY": 339.25, "maxX": 713.5, "maxY": 408.25}, "class_id": 3, "box_caption": "bus 0.004", "scores": {"class_score": 0.004207611083984375}, "domain": "pixel"}, {"position": {"minX": 572.5, "minY": 356.5, "maxX": 630.5, "maxY": 396.5}, "class_id": 2, "box_caption": "truck 0.004", "scores": {"class_score": 0.004169464111328125}, "domain": "pixel"}, {"position": {"minX": 722.0, "minY": 351.25, "maxX": 746.0, "maxY": 362.75}, "class_id": 0, "box_caption": "car 0.004", "scores": {"class_score": 0.004161834716796875}, "domain": "pixel"}, {"position": {"minX": 705.0, "minY": 348.0, "maxX": 729.0, "maxY": 372.0}, "class_id": 2, "box_caption": "truck 0.004", "scores": {"class_score": 0.00412750244140625}, "domain": "pixel"}, {"position": {"minX": 470.25, "minY": 351.5, "maxX": 576.0, "maxY": 420.0}, "class_id": 8, "box_caption": "caravan 0.004", "scores": {"class_score": 0.00408935546875}, "domain": "pixel"}, {"position": {"minX": 470.75, "minY": 351.25, "maxX": 575.5, "maxY": 419.75}, "class_id": 2, "box_caption": "truck 0.004", "scores": {"class_score": 0.0040283203125}, "domain": "pixel"}, {"position": {"minX": 710.5, "minY": 347.5, "maxX": 731.5, "maxY": 359.0}, "class_id": 0, "box_caption": "car 0.004", "scores": {"class_score": 0.003997802734375}, "domain": "pixel"}, {"position": {"minX": 249.125, "minY": 264.0, "maxX": 263.75, "maxY": 274.5}, "class_id": 0, "box_caption": "car 0.004", "scores": {"class_score": 0.003986358642578125}, "domain": "pixel"}, {"position": {"minX": 619.0, "minY": 357.75, "maxX": 636.0, "maxY": 366.75}, "class_id": 0, "box_caption": "car 0.004", "scores": {"class_score": 0.003940582275390625}, "domain": "pixel"}, {"position": {"minX": 100.25, "minY": 333.25, "maxX": 151.375, "maxY": 343.75}, "class_id": 0, "box_caption": "car 0.004", "scores": {"class_score": 0.0039043426513671875}, "domain": "pixel"}, {"position": {"minX": 479.25, "minY": 351.0, "maxX": 514.5, "maxY": 367.0}, "class_id": 0, "box_caption": "car 0.004", "scores": {"class_score": 0.003879547119140625}, "domain": "pixel"}, {"position": {"minX": 697.0, "minY": 362.75, "maxX": 716.0, "maxY": 390.25}, "class_id": 0, "box_caption": "car 0.004", "scores": {"class_score": 0.003841400146484375}, "domain": "pixel"}, {"position": {"minX": 123.625, "minY": 344.25, "maxX": 257.5, "maxY": 394.75}, "class_id": 0, "box_caption": "car 0.004", "scores": {"class_score": 0.003818511962890625}, "domain": "pixel"}, {"position": {"minX": 619.5, "minY": 362.75, "maxX": 641.5, "maxY": 392.75}, "class_id": 0, "box_caption": "car 0.004", "scores": {"class_score": 0.003711700439453125}, "domain": "pixel"}, {"position": {"minX": 470.5, "minY": 350.75, "maxX": 575.5, "maxY": 419.75}, "class_id": 1, "box_caption": "person 0.004", "scores": {"class_score": 0.0036296844482421875}, "domain": "pixel"}, {"position": {"minX": 308.5, "minY": 347.75, "maxX": 365.5, "maxY": 372.25}, "class_id": 0, "box_caption": "car 0.004", "scores": {"class_score": 0.0036106109619140625}, "domain": "pixel"}, {"position": {"minX": 716.0, "minY": 355.25, "maxX": 749.0, "maxY": 381.75}, "class_id": 3, "box_caption": "bus 0.004", "scores": {"class_score": 0.0036029815673828125}, "domain": "pixel"}, {"position": {"minX": 622.0, "minY": 359.0, "maxX": 644.0, "maxY": 376.0}, "class_id": 2, "box_caption": "truck 0.004", "scores": {"class_score": 0.0035800933837890625}, "domain": "pixel"}, {"position": {"minX": 716.0, "minY": 355.0, "maxX": 749.0, "maxY": 382.0}, "class_id": 8, "box_caption": "caravan 0.003", "scores": {"class_score": 0.0034008026123046875}, "domain": "pixel"}, {"position": {"minX": 638.0, "minY": 350.75, "maxX": 654.0, "maxY": 374.25}, "class_id": 0, "box_caption": "car 0.003", "scores": {"class_score": 0.00333404541015625}, "domain": "pixel"}, {"position": {"minX": 330.75, "minY": 348.75, "maxX": 364.25, "maxY": 363.25}, "class_id": 0, "box_caption": "car 0.003", "scores": {"class_score": 0.003307342529296875}, "domain": "pixel"}, {"position": {"minX": 639.0, "minY": 338.75, "maxX": 713.0, "maxY": 410.25}, "class_id": 8, "box_caption": "caravan 0.003", "scores": {"class_score": 0.0032958984375}, "domain": "pixel"}, {"position": {"minX": 306.5, "minY": 351.5, "maxX": 349.5, "maxY": 365.0}, "class_id": 0, "box_caption": "car 0.003", "scores": {"class_score": 0.003265380859375}, "domain": "pixel"}, {"position": {"minX": 546.5, "minY": 346.5, "maxX": 578.5, "maxY": 371.0}, "class_id": 0, "box_caption": "car 0.003", "scores": {"class_score": 0.0031147003173828125}, "domain": "pixel"}, {"position": {"minX": 470.75, "minY": 351.25, "maxX": 575.5, "maxY": 419.75}, "class_id": 4, "box_caption": "bicycle 0.003", "scores": {"class_score": 0.0030670166015625}, "domain": "pixel"}, {"position": {"minX": 470.75, "minY": 351.25, "maxX": 575.5, "maxY": 419.75}, "class_id": 5, "box_caption": "rider 0.003", "scores": {"class_score": 0.003021240234375}, "domain": "pixel"}, {"position": {"minX": 33.53125, "minY": 327.25, "maxX": 134.0, "maxY": 390.75}, "class_id": 0, "box_caption": "car 0.003", "scores": {"class_score": 0.0030155181884765625}, "domain": "pixel"}, {"position": {"minX": 343.75, "minY": 349.25, "maxX": 445.25, "maxY": 386.25}, "class_id": 2, "box_caption": "truck 0.003", "scores": {"class_score": 0.0029964447021484375}, "domain": "pixel"}, {"position": {"minX": 576.0, "minY": 355.5, "maxX": 615.0, "maxY": 376.5}, "class_id": 0, "box_caption": "car 0.003", "scores": {"class_score": 0.0029888153076171875}, "domain": "pixel"}, {"position": {"minX": 470.75, "minY": 351.25, "maxX": 575.5, "maxY": 419.75}, "class_id": 7, "box_caption": "motorcycle 0.003", "scores": {"class_score": 0.0029506683349609375}, "domain": "pixel"}, {"position": {"minX": 757.0, "minY": 360.5, "maxX": 769.0, "maxY": 370.5}, "class_id": 0, "box_caption": "car 0.003", "scores": {"class_score": 0.002941131591796875}, "domain": "pixel"}, {"position": {"minX": 572.5, "minY": 356.5, "maxX": 630.5, "maxY": 396.5}, "class_id": 8, "box_caption": "caravan 0.003", "scores": {"class_score": 0.002925872802734375}, "domain": "pixel"}, {"position": {"minX": 580.0, "minY": 354.5, "maxX": 602.0, "maxY": 366.0}, "class_id": 0, "box_caption": "car 0.003", "scores": {"class_score": 0.00290679931640625}, "domain": "pixel"}, {"position": {"minX": 714.5, "minY": 348.0, "maxX": 779.5, "maxY": 380.5}, "class_id": 0, "box_caption": "car 0.003", "scores": {"class_score": 0.002819061279296875}, "domain": "pixel"}, {"position": {"minX": 430.5, "minY": 343.5, "maxX": 486.0, "maxY": 364.5}, "class_id": 0, "box_caption": "car 0.003", "scores": {"class_score": 0.0028133392333984375}, "domain": "pixel"}, {"position": {"minX": 730.5, "minY": 352.25, "maxX": 758.5, "maxY": 364.75}, "class_id": 0, "box_caption": "car 0.003", "scores": {"class_score": 0.002811431884765625}, "domain": "pixel"}, {"position": {"minX": 764.5, "minY": 355.5, "maxX": 785.5, "maxY": 369.5}, "class_id": 3, "box_caption": "bus 0.003", "scores": {"class_score": 0.0028076171875}, "domain": "pixel"}, {"position": {"minX": 739.5, "minY": 355.5, "maxX": 763.5, "maxY": 375.0}, "class_id": 2, "box_caption": "truck 0.003", "scores": {"class_score": 0.0027713775634765625}, "domain": "pixel"}, {"position": {"minX": 501.0, "minY": 348.5, "maxX": 531.0, "maxY": 357.0}, "class_id": 0, "box_caption": "car 0.003", "scores": {"class_score": 0.002758026123046875}, "domain": "pixel"}, {"position": {"minX": 572.0, "minY": 356.75, "maxX": 631.0, "maxY": 396.25}, "class_id": 3, "box_caption": "bus 0.003", "scores": {"class_score": 0.00273895263671875}, "domain": "pixel"}, {"position": {"minX": 638.5, "minY": 339.25, "maxX": 712.5, "maxY": 410.25}, "class_id": 1, "box_caption": "person 0.003", "scores": {"class_score": 0.0026988983154296875}, "domain": "pixel"}, {"position": {"minX": 548.0, "minY": 353.0, "maxX": 577.0, "maxY": 375.0}, "class_id": 2, "box_caption": "truck 0.003", "scores": {"class_score": 0.0026798248291015625}, "domain": "pixel"}, {"position": {"minX": 562.0, "minY": 350.5, "maxX": 615.0, "maxY": 369.5}, "class_id": 0, "box_caption": "car 0.003", "scores": {"class_score": 0.00267791748046875}, "domain": "pixel"}, {"position": {"minX": -103.0, "minY": 612.0, "maxX": 1294.0, "maxY": 778.0}, "class_id": 0, "box_caption": "car 0.003", "scores": {"class_score": 0.0026092529296875}, "domain": "pixel"}, {"position": {"minX": 54.25, "minY": 337.25, "maxX": 208.5, "maxY": 391.75}, "class_id": 0, "box_caption": "car 0.003", "scores": {"class_score": 0.0026073455810546875}, "domain": "pixel"}, {"position": {"minX": 470.75, "minY": 351.25, "maxX": 575.5, "maxY": 419.75}, "class_id": 9, "box_caption": "train 0.003", "scores": {"class_score": 0.002605438232421875}, "domain": "pixel"}, {"position": {"minX": 572.5, "minY": 356.5, "maxX": 630.5, "maxY": 396.5}, "class_id": 4, "box_caption": "bicycle 0.003", "scores": {"class_score": 0.0025920867919921875}, "domain": "pixel"}, {"position": {"minX": 92.5, "minY": 268.75, "maxX": 154.75, "maxY": 294.75}, "class_id": 0, "box_caption": "car 0.003", "scores": {"class_score": 0.0025653839111328125}, "domain": "pixel"}, {"position": {"minX": 607.0, "minY": 354.75, "maxX": 626.0, "maxY": 365.75}, "class_id": 0, "box_caption": "car 0.003", "scores": {"class_score": 0.0025577545166015625}, "domain": "pixel"}, {"position": {"minX": 797.0, "minY": 345.25, "maxX": 813.0, "maxY": 357.75}, "class_id": 0, "box_caption": "car 0.002", "scores": {"class_score": 0.0024852752685546875}, "domain": "pixel"}, {"position": {"minX": 470.75, "minY": 351.25, "maxX": 575.5, "maxY": 419.75}, "class_id": 6, "box_caption": "trailer 0.002", "scores": {"class_score": 0.0024662017822265625}, "domain": "pixel"}, {"position": {"minX": 631.0, "minY": 345.0, "maxX": 686.0, "maxY": 400.5}, "class_id": 0, "box_caption": "car 0.002", "scores": {"class_score": 0.0024261474609375}, "domain": "pixel"}, {"position": {"minX": 639.0, "minY": 338.75, "maxX": 713.0, "maxY": 410.25}, "class_id": 4, "box_caption": "bicycle 0.002", "scores": {"class_score": 0.002422332763671875}, "domain": "pixel"}, {"position": {"minX": 639.0, "minY": 338.75, "maxX": 713.0, "maxY": 410.25}, "class_id": 7, "box_caption": "motorcycle 0.002", "scores": {"class_score": 0.002414703369140625}, "domain": "pixel"}, {"position": {"minX": 703.0, "minY": 348.75, "maxX": 727.0, "maxY": 383.25}, "class_id": 3, "box_caption": "bus 0.002", "scores": {"class_score": 0.0023651123046875}, "domain": "pixel"}, {"position": {"minX": 37.09375, "minY": 292.75, "maxX": 83.125, "maxY": 315.25}, "class_id": 0, "box_caption": "car 0.002", "scores": {"class_score": 0.002361297607421875}, "domain": "pixel"}, {"position": {"minX": 716.0, "minY": 356.5, "maxX": 748.0, "maxY": 381.5}, "class_id": 1, "box_caption": "person 0.002", "scores": {"class_score": 0.0023517608642578125}, "domain": "pixel"}, {"position": {"minX": 371.0, "minY": 348.75, "maxX": 445.0, "maxY": 378.25}, "class_id": 0, "box_caption": "car 0.002", "scores": {"class_score": 0.0022716522216796875}, "domain": "pixel"}, {"position": {"minX": 634.0, "minY": 344.25, "maxX": 651.0, "maxY": 361.75}, "class_id": 0, "box_caption": "car 0.002", "scores": {"class_score": 0.0022525787353515625}, "domain": "pixel"}, {"position": {"minX": 572.0, "minY": 356.75, "maxX": 631.0, "maxY": 396.25}, "class_id": 1, "box_caption": "person 0.002", "scores": {"class_score": 0.002227783203125}, "domain": "pixel"}, {"position": {"minX": 633.5, "minY": 363.25, "maxX": 648.5, "maxY": 386.75}, "class_id": 0, "box_caption": "car 0.002", "scores": {"class_score": 0.0022220611572265625}, "domain": "pixel"}, {"position": {"minX": 639.5, "minY": 339.5, "maxX": 713.5, "maxY": 410.0}, "class_id": 9, "box_caption": "train 0.002", "scores": {"class_score": 0.00222015380859375}, "domain": "pixel"}, {"position": {"minX": 188.0, "minY": 350.0, "maxX": 265.0, "maxY": 388.0}, "class_id": 0, "box_caption": "car 0.002", "scores": {"class_score": 0.00218963623046875}, "domain": "pixel"}, {"position": {"minX": 607.0, "minY": 352.25, "maxX": 630.0, "maxY": 364.25}, "class_id": 0, "box_caption": "car 0.002", "scores": {"class_score": 0.0021877288818359375}, "domain": "pixel"}, {"position": {"minX": 459.75, "minY": 348.5, "maxX": 490.75, "maxY": 362.0}, "class_id": 0, "box_caption": "car 0.002", "scores": {"class_score": 0.0021800994873046875}, "domain": "pixel"}, {"position": {"minX": 707.5, "minY": 372.25, "maxX": 717.5, "maxY": 390.25}, "class_id": 0, "box_caption": "car 0.002", "scores": {"class_score": 0.0020751953125}, "domain": "pixel"}, {"position": {"minX": 617.5, "minY": 355.5, "maxX": 637.5, "maxY": 369.0}, "class_id": 0, "box_caption": "car 0.002", "scores": {"class_score": 0.0020751953125}, "domain": "pixel"}, {"position": {"minX": 796.0, "minY": 347.75, "maxX": 810.0, "maxY": 359.25}, "class_id": 0, "box_caption": "car 0.002", "scores": {"class_score": 0.0020656585693359375}, "domain": "pixel"}, {"position": {"minX": 517.0, "minY": 350.0, "maxX": 565.0, "maxY": 363.5}, "class_id": 0, "box_caption": "car 0.002", "scores": {"class_score": 0.002040863037109375}, "domain": "pixel"}, {"position": {"minX": 575.0, "minY": 355.5, "maxX": 597.0, "maxY": 367.5}, "class_id": 0, "box_caption": "car 0.002", "scores": {"class_score": 0.0020351409912109375}, "domain": "pixel"}, {"position": {"minX": 708.5, "minY": 355.5, "maxX": 737.5, "maxY": 379.5}, "class_id": 2, "box_caption": "truck 0.002", "scores": {"class_score": 0.0020351409912109375}, "domain": "pixel"}, {"position": {"minX": 162.0, "minY": 344.25, "maxX": 263.5, "maxY": 384.25}, "class_id": 2, "box_caption": "truck 0.002", "scores": {"class_score": 0.0020313262939453125}, "domain": "pixel"}, {"position": {"minX": 703.0, "minY": 349.0, "maxX": 727.0, "maxY": 384.0}, "class_id": 8, "box_caption": "caravan 0.002", "scores": {"class_score": 0.0020198822021484375}, "domain": "pixel"}, {"position": {"minX": 572.5, "minY": 356.5, "maxX": 630.5, "maxY": 396.5}, "class_id": 9, "box_caption": "train 0.002", "scores": {"class_score": 0.00200653076171875}, "domain": "pixel"}, {"position": {"minX": 639.5, "minY": 339.5, "maxX": 713.5, "maxY": 410.0}, "class_id": 5, "box_caption": "rider 0.002", "scores": {"class_score": 0.0019969940185546875}, "domain": "pixel"}, {"position": {"minX": 320.75, "minY": 344.75, "maxX": 438.25, "maxY": 378.25}, "class_id": 0, "box_caption": "car 0.002", "scores": {"class_score": 0.0019931793212890625}, "domain": "pixel"}, {"position": {"minX": 343.0, "minY": 349.5, "maxX": 444.0, "maxY": 387.5}, "class_id": 3, "box_caption": "bus 0.002", "scores": {"class_score": 0.001972198486328125}, "domain": "pixel"}, {"position": {"minX": 705.0, "minY": 347.75, "maxX": 729.0, "maxY": 371.75}, "class_id": 3, "box_caption": "bus 0.002", "scores": {"class_score": 0.0019321441650390625}, "domain": "pixel"}, {"position": {"minX": 88.3125, "minY": 264.5, "maxX": 147.875, "maxY": 286.5}, "class_id": 0, "box_caption": "car 0.002", "scores": {"class_score": 0.0019273757934570312}, "domain": "pixel"}, {"position": {"minX": 744.0, "minY": 354.75, "maxX": 766.0, "maxY": 371.25}, "class_id": 2, "box_caption": "truck 0.002", "scores": {"class_score": 0.0019197463989257812}, "domain": "pixel"}, {"position": {"minX": 695.5, "minY": 343.75, "maxX": 713.5, "maxY": 371.75}, "class_id": 0, "box_caption": "car 0.002", "scores": {"class_score": 0.0018863677978515625}, "domain": "pixel"}, {"position": {"minX": 99.375, "minY": 279.0, "maxX": 148.375, "maxY": 295.0}, "class_id": 0, "box_caption": "car 0.002", "scores": {"class_score": 0.0018758773803710938}, "domain": "pixel"}, {"position": {"minX": 716.0, "minY": 355.0, "maxX": 749.0, "maxY": 382.0}, "class_id": 6, "box_caption": "trailer 0.002", "scores": {"class_score": 0.0018663406372070312}, "domain": "pixel"}, {"position": {"minX": 572.5, "minY": 356.5, "maxX": 630.5, "maxY": 396.5}, "class_id": 7, "box_caption": "motorcycle 0.002", "scores": {"class_score": 0.0018568038940429688}, "domain": "pixel"}, {"position": {"minX": 433.75, "minY": 358.0, "maxX": 482.75, "maxY": 380.0}, "class_id": 2, "box_caption": "truck 0.002", "scores": {"class_score": 0.0018301010131835938}, "domain": "pixel"}, {"position": {"minX": 42.65625, "minY": 287.25, "maxX": 95.25, "maxY": 312.75}, "class_id": 0, "box_caption": "car 0.002", "scores": {"class_score": 0.0018291473388671875}, "domain": "pixel"}, {"position": {"minX": 778.5, "minY": 354.25, "maxX": 789.5, "maxY": 365.25}, "class_id": 0, "box_caption": "car 0.002", "scores": {"class_score": 0.0018215179443359375}, "domain": "pixel"}, {"position": {"minX": 572.0, "minY": 356.75, "maxX": 631.0, "maxY": 396.25}, "class_id": 6, "box_caption": "trailer 0.002", "scores": {"class_score": 0.001811981201171875}, "domain": "pixel"}, {"position": {"minX": 30.0, "minY": 279.25, "maxX": 72.25, "maxY": 312.25}, "class_id": 0, "box_caption": "car 0.002", "scores": {"class_score": 0.0017948150634765625}, "domain": "pixel"}, {"position": {"minX": 343.0, "minY": 349.5, "maxX": 444.0, "maxY": 387.5}, "class_id": 9, "box_caption": "train 0.002", "scores": {"class_score": 0.0017900466918945312}, "domain": "pixel"}, {"position": {"minX": 622.0, "minY": 359.0, "maxX": 644.0, "maxY": 376.0}, "class_id": 3, "box_caption": "bus 0.002", "scores": {"class_score": 0.0017862319946289062}, "domain": "pixel"}, {"position": {"minX": 344.0, "minY": 348.75, "maxX": 446.0, "maxY": 387.75}, "class_id": 4, "box_caption": "bicycle 0.002", "scores": {"class_score": 0.001758575439453125}, "domain": "pixel"}, {"position": {"minX": 572.5, "minY": 356.5, "maxX": 630.5, "maxY": 396.5}, "class_id": 5, "box_caption": "rider 0.002", "scores": {"class_score": 0.001758575439453125}, "domain": "pixel"}, {"position": {"minX": 577.5, "minY": 356.75, "maxX": 628.5, "maxY": 382.25}, "class_id": 0, "box_caption": "car 0.002", "scores": {"class_score": 0.0017528533935546875}, "domain": "pixel"}, {"position": {"minX": 45.625, "minY": 334.75, "maxX": 170.375, "maxY": 373.25}, "class_id": 0, "box_caption": "car 0.002", "scores": {"class_score": 0.0017518997192382812}, "domain": "pixel"}, {"position": {"minX": 343.0, "minY": 349.5, "maxX": 444.0, "maxY": 387.5}, "class_id": 8, "box_caption": "caravan 0.002", "scores": {"class_score": 0.0017080307006835938}, "domain": "pixel"}, {"position": {"minX": 495.0, "minY": 347.75, "maxX": 526.0, "maxY": 358.25}, "class_id": 0, "box_caption": "car 0.002", "scores": {"class_score": 0.0016927719116210938}, "domain": "pixel"}, {"position": {"minX": 630.0, "minY": 343.0, "maxX": 656.0, "maxY": 364.5}, "class_id": 0, "box_caption": "car 0.002", "scores": {"class_score": 0.0016889572143554688}, "domain": "pixel"}, {"position": {"minX": 739.5, "minY": 355.5, "maxX": 763.5, "maxY": 375.0}, "class_id": 3, "box_caption": "bus 0.002", "scores": {"class_score": 0.0016727447509765625}, "domain": "pixel"}, {"position": {"minX": 296.75, "minY": 256.5, "maxX": 311.25, "maxY": 266.5}, "class_id": 0, "box_caption": "car 0.002", "scores": {"class_score": 0.0016603469848632812}, "domain": "pixel"}, {"position": {"minX": 462.75, "minY": 334.75, "maxX": 588.5, "maxY": 432.25}, "class_id": 0, "box_caption": "car 0.002", "scores": {"class_score": 0.0016508102416992188}, "domain": "pixel"}, {"position": {"minX": 638.5, "minY": 339.5, "maxX": 713.5, "maxY": 409.5}, "class_id": 6, "box_caption": "trailer 0.002", "scores": {"class_score": 0.0016326904296875}, "domain": "pixel"}, {"position": {"minX": 716.0, "minY": 355.0, "maxX": 749.0, "maxY": 382.0}, "class_id": 7, "box_caption": "motorcycle 0.002", "scores": {"class_score": 0.0016222000122070312}, "domain": "pixel"}, {"position": {"minX": 716.0, "minY": 355.25, "maxX": 749.0, "maxY": 381.75}, "class_id": 5, "box_caption": "rider 0.002", "scores": {"class_score": 0.0016155242919921875}, "domain": "pixel"}, {"position": {"minX": 548.0, "minY": 353.0, "maxX": 577.0, "maxY": 375.0}, "class_id": 3, "box_caption": "bus 0.002", "scores": {"class_score": 0.0016155242919921875}, "domain": "pixel"}, {"position": {"minX": 286.5, "minY": 254.0, "maxX": 311.5, "maxY": 267.0}, "class_id": 0, "box_caption": "car 0.002", "scores": {"class_score": 0.0016107559204101562}, "domain": "pixel"}, {"position": {"minX": 716.0, "minY": 355.5, "maxX": 749.0, "maxY": 381.5}, "class_id": 4, "box_caption": "bicycle 0.002", "scores": {"class_score": 0.0016107559204101562}, "domain": "pixel"}, {"position": {"minX": 791.5, "minY": 350.5, "maxX": 806.5, "maxY": 363.5}, "class_id": 0, "box_caption": "car 0.002", "scores": {"class_score": 0.0015869140625}, "domain": "pixel"}, {"position": {"minX": 451.25, "minY": 347.0, "maxX": 486.25, "maxY": 361.5}, "class_id": 0, "box_caption": "car 0.002", "scores": {"class_score": 0.0015802383422851562}, "domain": "pixel"}, {"position": {"minX": 705.0, "minY": 356.5, "maxX": 723.0, "maxY": 384.5}, "class_id": 2, "box_caption": "truck 0.002", "scores": {"class_score": 0.0015649795532226562}, "domain": "pixel"}, {"position": {"minX": 703.0, "minY": 351.25, "maxX": 723.0, "maxY": 385.25}, "class_id": 1, "box_caption": "person 0.002", "scores": {"class_score": 0.0015354156494140625}, "domain": "pixel"}, {"position": {"minX": 98.625, "minY": 332.75, "maxX": 160.375, "maxY": 347.25}, "class_id": 0, "box_caption": "car 0.002", "scores": {"class_score": 0.0015268325805664062}, "domain": "pixel"}, {"position": {"minX": 29.375, "minY": 267.0, "maxX": 93.9375, "maxY": 301.5}, "class_id": 0, "box_caption": "car 0.002", "scores": {"class_score": 0.0015134811401367188}, "domain": "pixel"}, {"position": {"minX": 40.3125, "minY": 300.75, "maxX": 77.25, "maxY": 319.75}, "class_id": 0, "box_caption": "car 0.002", "scores": {"class_score": 0.001506805419921875}, "domain": "pixel"}, {"position": {"minX": 599.5, "minY": 320.0, "maxX": 750.5, "maxY": 433.0}, "class_id": 0, "box_caption": "car 0.001", "scores": {"class_score": 0.0014972686767578125}, "domain": "pixel"}, {"position": {"minX": 82.75, "minY": 272.25, "maxX": 138.0, "maxY": 292.25}, "class_id": 0, "box_caption": "car 0.001", "scores": {"class_score": 0.0014963150024414062}, "domain": "pixel"}, {"position": {"minX": 104.5, "minY": 339.75, "maxX": 245.75, "maxY": 382.75}, "class_id": 0, "box_caption": "car 0.001", "scores": {"class_score": 0.0014934539794921875}, "domain": "pixel"}, {"position": {"minX": 707.0, "minY": 348.75, "maxX": 730.0, "maxY": 362.75}, "class_id": 3, "box_caption": "bus 0.001", "scores": {"class_score": 0.001491546630859375}, "domain": "pixel"}, {"position": {"minX": 402.0, "minY": 348.5, "maxX": 478.0, "maxY": 370.5}, "class_id": 0, "box_caption": "car 0.001", "scores": {"class_score": 0.0014848709106445312}, "domain": "pixel"}, {"position": {"minX": 344.0, "minY": 349.25, "maxX": 446.0, "maxY": 387.75}, "class_id": 7, "box_caption": "motorcycle 0.001", "scores": {"class_score": 0.0014753341674804688}, "domain": "pixel"}, {"position": {"minX": 629.0, "minY": 343.75, "maxX": 647.0, "maxY": 362.75}, "class_id": 0, "box_caption": "car 0.001", "scores": {"class_score": 0.0014696121215820312}, "domain": "pixel"}, {"position": {"minX": 247.5, "minY": 266.25, "maxX": 263.5, "maxY": 278.25}, "class_id": 0, "box_caption": "car 0.001", "scores": {"class_score": 0.001453399658203125}, "domain": "pixel"}, {"position": {"minX": 249.5, "minY": 265.0, "maxX": 269.0, "maxY": 278.0}, "class_id": 0, "box_caption": "car 0.001", "scores": {"class_score": 0.0014133453369140625}, "domain": "pixel"}, {"position": {"minX": 763.5, "minY": 354.5, "maxX": 786.5, "maxY": 370.0}, "class_id": 8, "box_caption": "caravan 0.001", "scores": {"class_score": 0.0013980865478515625}, "domain": "pixel"}, {"position": {"minX": 716.0, "minY": 355.25, "maxX": 749.0, "maxY": 381.75}, "class_id": 9, "box_caption": "train 0.001", "scores": {"class_score": 0.0013885498046875}, "domain": "pixel"}, {"position": {"minX": 343.75, "minY": 349.25, "maxX": 445.25, "maxY": 386.25}, "class_id": 1, "box_caption": "person 0.001", "scores": {"class_score": 0.0013799667358398438}, "domain": "pixel"}, {"position": {"minX": 84.625, "minY": 245.0, "maxX": 128.375, "maxY": 274.5}, "class_id": 0, "box_caption": "car 0.001", "scores": {"class_score": 0.001369476318359375}, "domain": "pixel"}, {"position": {"minX": 97.625, "minY": 246.125, "maxX": 124.75, "maxY": 259.75}, "class_id": 0, "box_caption": "car 0.001", "scores": {"class_score": 0.0013599395751953125}, "domain": "pixel"}, {"position": {"minX": 32.9375, "minY": 280.75, "maxX": 90.6875, "maxY": 307.75}, "class_id": 0, "box_caption": "car 0.001", "scores": {"class_score": 0.0013589859008789062}, "domain": "pixel"}, {"position": {"minX": 433.75, "minY": 358.0, "maxX": 482.75, "maxY": 380.0}, "class_id": 3, "box_caption": "bus 0.001", "scores": {"class_score": 0.0013399124145507812}, "domain": "pixel"}, {"position": {"minX": 625.0, "minY": 342.0, "maxX": 663.0, "maxY": 370.5}, "class_id": 0, "box_caption": "car 0.001", "scores": {"class_score": 0.0013360977172851562}, "domain": "pixel"}, {"position": {"minX": 158.5, "minY": 337.25, "maxX": 405.5, "maxY": 395.75}, "class_id": 0, "box_caption": "car 0.001", "scores": {"class_score": 0.0013275146484375}, "domain": "pixel"}, {"position": {"minX": 342.5, "minY": 349.0, "maxX": 445.0, "maxY": 388.0}, "class_id": 6, "box_caption": "trailer 0.001", "scores": {"class_score": 0.0013055801391601562}, "domain": "pixel"}, {"position": {"minX": 763.5, "minY": 355.0, "maxX": 786.5, "maxY": 370.5}, "class_id": 4, "box_caption": "bicycle 0.001", "scores": {"class_score": 0.001300811767578125}, "domain": "pixel"}, {"position": {"minX": 162.125, "minY": 344.25, "maxX": 263.5, "maxY": 385.25}, "class_id": 3, "box_caption": "bus 0.001", "scores": {"class_score": 0.0012903213500976562}, "domain": "pixel"}, {"position": {"minX": 379.75, "minY": 347.75, "maxX": 443.25, "maxY": 368.25}, "class_id": 0, "box_caption": "car 0.001", "scores": {"class_score": 0.0012731552124023438}, "domain": "pixel"}, {"position": {"minX": 705.0, "minY": 356.5, "maxX": 723.0, "maxY": 384.5}, "class_id": 3, "box_caption": "bus 0.001", "scores": {"class_score": 0.0012607574462890625}, "domain": "pixel"}, {"position": {"minX": 179.375, "minY": 344.25, "maxX": 256.5, "maxY": 374.25}, "class_id": 0, "box_caption": "car 0.001", "scores": {"class_score": 0.0012598037719726562}, "domain": "pixel"}, {"position": {"minX": 703.0, "minY": 369.75, "maxX": 717.0, "maxY": 391.25}, "class_id": 0, "box_caption": "car 0.001", "scores": {"class_score": 0.0012426376342773438}, "domain": "pixel"}, {"position": {"minX": 22.6875, "minY": 336.0, "maxX": 219.5, "maxY": 402.0}, "class_id": 2, "box_caption": "truck 0.001", "scores": {"class_score": 0.0012426376342773438}, "domain": "pixel"}, {"position": {"minX": 637.0, "minY": 341.5, "maxX": 701.0, "maxY": 392.0}, "class_id": 0, "box_caption": "car 0.001", "scores": {"class_score": 0.0012273788452148438}, "domain": "pixel"}, {"position": {"minX": 343.0, "minY": 349.5, "maxX": 444.0, "maxY": 387.5}, "class_id": 5, "box_caption": "rider 0.001", "scores": {"class_score": 0.0011882781982421875}, "domain": "pixel"}, {"position": {"minX": 333.75, "minY": 349.75, "maxX": 362.75, "maxY": 358.75}, "class_id": 0, "box_caption": "car 0.001", "scores": {"class_score": 0.0011653900146484375}, "domain": "pixel"}, {"position": {"minX": 26.890625, "minY": 294.0, "maxX": 85.5, "maxY": 327.5}, "class_id": 0, "box_caption": "car 0.001", "scores": {"class_score": 0.0011529922485351562}, "domain": "pixel"}, {"position": {"minX": 453.25, "minY": 345.5, "maxX": 521.0, "maxY": 378.0}, "class_id": 0, "box_caption": "car 0.001", "scores": {"class_score": 0.0011272430419921875}, "domain": "pixel"}, {"position": {"minX": 474.0, "minY": 347.75, "maxX": 531.5, "maxY": 375.25}, "class_id": 0, "box_caption": "car 0.001", "scores": {"class_score": 0.0011262893676757812}, "domain": "pixel"}, {"position": {"minX": 762.5, "minY": 360.5, "maxX": 788.5, "maxY": 379.0}, "class_id": 0, "box_caption": "car 0.001", "scores": {"class_score": 0.0011262893676757812}, "domain": "pixel"}, {"position": {"minX": 683.5, "minY": 338.75, "maxX": 718.5, "maxY": 365.25}, "class_id": 0, "box_caption": "car 0.001", "scores": {"class_score": 0.001117706298828125}, "domain": "pixel"}, {"position": {"minX": 1117.0, "minY": 175.25, "maxX": 1163.0, "maxY": 196.25}, "class_id": 0, "box_caption": "car 0.001", "scores": {"class_score": 0.0011053085327148438}, "domain": "pixel"}, {"position": {"minX": 553.5, "minY": 350.5, "maxX": 572.5, "maxY": 359.5}, "class_id": 0, "box_caption": "car 0.001", "scores": {"class_score": 0.0010957717895507812}, "domain": "pixel"}, {"position": {"minX": 529.0, "minY": 349.25, "maxX": 558.0, "maxY": 361.75}, "class_id": 0, "box_caption": "car 0.001", "scores": {"class_score": 0.0010890960693359375}, "domain": "pixel"}, {"position": {"minX": 162.125, "minY": 344.25, "maxX": 263.5, "maxY": 385.25}, "class_id": 4, "box_caption": "bicycle 0.001", "scores": {"class_score": 0.001087188720703125}, "domain": "pixel"}, {"position": {"minX": 433.75, "minY": 358.0, "maxX": 482.75, "maxY": 380.0}, "class_id": 4, "box_caption": "bicycle 0.001", "scores": {"class_score": 0.001079559326171875}, "domain": "pixel"}, {"position": {"minX": 482.0, "minY": 346.5, "maxX": 560.0, "maxY": 365.5}, "class_id": 0, "box_caption": "car 0.001", "scores": {"class_score": 0.0010738372802734375}, "domain": "pixel"}, {"position": {"minX": 95.375, "minY": 246.625, "maxX": 130.625, "maxY": 264.75}, "class_id": 0, "box_caption": "car 0.001", "scores": {"class_score": 0.0010728836059570312}, "domain": "pixel"}, {"position": {"minX": 162.125, "minY": 344.25, "maxX": 263.5, "maxY": 385.25}, "class_id": 9, "box_caption": "train 0.001", "scores": {"class_score": 0.0010499954223632812}, "domain": "pixel"}, {"position": {"minX": 89.8125, "minY": 341.0, "maxX": 261.0, "maxY": 407.5}, "class_id": 0, "box_caption": "car 0.001", "scores": {"class_score": 0.0010356903076171875}, "domain": "pixel"}, {"position": {"minX": 461.75, "minY": 345.5, "maxX": 505.75, "maxY": 369.5}, "class_id": 0, "box_caption": "car 0.001", "scores": {"class_score": 0.0010328292846679688}, "domain": "pixel"}, {"position": {"minX": 764.5, "minY": 355.5, "maxX": 785.5, "maxY": 369.5}, "class_id": 1, "box_caption": "person 0.001", "scores": {"class_score": 0.0010280609130859375}, "domain": "pixel"}, {"position": {"minX": 697.0, "minY": 343.5, "maxX": 717.0, "maxY": 357.5}, "class_id": 0, "box_caption": "car 0.001", "scores": {"class_score": 0.0010232925415039062}, "domain": "pixel"}, {"position": {"minX": 424.0, "minY": 360.0, "maxX": 471.5, "maxY": 382.5}, "class_id": 0, "box_caption": "car 0.001", "scores": {"class_score": 0.0010204315185546875}, "domain": "pixel"}, {"position": {"minX": 528.5, "minY": 344.0, "maxX": 566.5, "maxY": 359.0}, "class_id": 0, "box_caption": "car 0.001", "scores": {"class_score": 0.0010194778442382812}, "domain": "pixel"}, {"position": {"minX": 90.125, "minY": 244.25, "maxX": 124.5, "maxY": 263.25}, "class_id": 0, "box_caption": "car 0.001", "scores": {"class_score": 0.0010089874267578125}, "domain": "pixel"}, {"position": {"minX": 433.75, "minY": 358.0, "maxX": 482.75, "maxY": 380.0}, "class_id": 8, "box_caption": "caravan 0.001", "scores": {"class_score": 0.0010042190551757812}, "domain": "pixel"}, {"position": {"minX": 103.0, "minY": 276.5, "maxX": 159.5, "maxY": 298.0}, "class_id": 0, "box_caption": "car 0.001", "scores": {"class_score": 0.0010023117065429688}, "domain": "pixel"}], "class_labels": {"0": "car", "1": "person", "2": "truck", "3": "bus", "4": "bicycle", "5": "rider", "6": "trailer", "7": "motorcycle", "8": "caravan", "9": "train"}}