{"box_data": [{"position": {"minX": 31.375, "minY": 384.0, "maxX": 386.5, "maxY": 591.5}, "class_id": 2, "box_caption": "car 0.956", "scores": {"class_score": 0.9560546875}, "domain": "pixel"}, {"position": {"minX": 825.5, "minY": 429.5, "maxX": 869.5, "maxY": 459.0}, "class_id": 2, "box_caption": "car 0.917", "scores": {"class_score": 0.91748046875}, "domain": "pixel"}, {"position": {"minX": 935.0, "minY": 402.0, "maxX": 975.0, "maxY": 492.5}, "class_id": 4, "box_caption": "pedestrian 0.897", "scores": {"class_score": 0.8974609375}, "domain": "pixel"}, {"position": {"minX": 755.0, "minY": 427.0, "maxX": 784.0, "maxY": 453.0}, "class_id": 2, "box_caption": "car 0.873", "scores": {"class_score": 0.873046875}, "domain": "pixel"}, {"position": {"minX": 1071.0, "minY": 407.25, "maxX": 1091.0, "maxY": 461.75}, "class_id": 4, "box_caption": "pedestrian 0.805", "scores": {"class_score": 0.8046875}, "domain": "pixel"}, {"position": {"minX": 785.0, "minY": 428.0, "maxX": 811.0, "maxY": 448.0}, "class_id": 2, "box_caption": "car 0.793", "scores": {"class_score": 0.79345703125}, "domain": "pixel"}, {"position": {"minX": 920.5, "minY": 418.0, "maxX": 934.5, "maxY": 450.5}, "class_id": 4, "box_caption": "pedestrian 0.756", "scores": {"class_score": 0.755859375}, "domain": "pixel"}, {"position": {"minX": 418.25, "minY": 414.0, "maxX": 442.25, "maxY": 478.5}, "class_id": 4, "box_caption": "pedestrian 0.739", "scores": {"class_score": 0.7392578125}, "domain": "pixel"}, {"position": {"minX": 646.5, "minY": 417.5, "maxX": 660.5, "maxY": 457.5}, "class_id": 4, "box_caption": "pedestrian 0.738", "scores": {"class_score": 0.73828125}, "domain": "pixel"}, {"position": {"minX": 307.25, "minY": 418.0, "maxX": 429.25, "maxY": 537.0}, "class_id": 2, "box_caption": "car 0.629", "scores": {"class_score": 0.62890625}, "domain": "pixel"}, {"position": {"minX": 877.0, "minY": 424.0, "maxX": 886.0, "maxY": 450.0}, "class_id": 4, "box_caption": "pedestrian 0.460", "scores": {"class_score": 0.46044921875}, "domain": "pixel"}, {"position": {"minX": 755.5, "minY": 428.0, "maxX": 804.5, "maxY": 451.0}, "class_id": 2, "box_caption": "car 0.358", "scores": {"class_score": 0.3583984375}, "domain": "pixel"}, {"position": {"minX": 817.5, "minY": 433.0, "maxX": 829.5, "maxY": 447.5}, "class_id": 2, "box_caption": "car 0.340", "scores": {"class_score": 0.33984375}, "domain": "pixel"}, {"position": {"minX": 464.5, "minY": 415.0, "maxX": 485.0, "maxY": 472.5}, "class_id": 4, "box_caption": "pedestrian 0.311", "scores": {"class_score": 0.310546875}, "domain": "pixel"}, {"position": {"minX": 481.5, "minY": 415.0, "maxX": 501.0, "maxY": 473.5}, "class_id": 4, "box_caption": "pedestrian 0.258", "scores": {"class_score": 0.2578125}, "domain": "pixel"}, {"position": {"minX": 466.5, "minY": 416.25, "maxX": 499.5, "maxY": 472.25}, "class_id": 4, "box_caption": "pedestrian 0.198", "scores": {"class_score": 0.1982421875}, "domain": "pixel"}, {"position": {"minX": 783.5, "minY": 428.5, "maxX": 867.5, "maxY": 457.0}, "class_id": 2, "box_caption": "car 0.196", "scores": {"class_score": 0.1956787109375}, "domain": "pixel"}, {"position": {"minX": 932.5, "minY": 417.0, "maxX": 944.5, "maxY": 449.0}, "class_id": 4, "box_caption": "pedestrian 0.165", "scores": {"class_score": 0.165283203125}, "domain": "pixel"}, {"position": {"minX": 873.5, "minY": 424.0, "maxX": 882.5, "maxY": 452.0}, "class_id": 4, "box_caption": "pedestrian 0.164", "scores": {"class_score": 0.1644287109375}, "domain": "pixel"}, {"position": {"minX": 411.25, "minY": 414.25, "maxX": 434.75, "maxY": 481.75}, "class_id": 4, "box_caption": "pedestrian 0.155", "scores": {"class_score": 0.1549072265625}, "domain": "pixel"}, {"position": {"minX": 365.0, "minY": 410.0, "maxX": 382.0, "maxY": 426.0}, "class_id": 4, "box_caption": "pedestrian 0.150", "scores": {"class_score": 0.1497802734375}, "domain": "pixel"}, {"position": {"minX": 640.0, "minY": 418.5, "maxX": 653.0, "maxY": 454.0}, "class_id": 4, "box_caption": "pedestrian 0.121", "scores": {"class_score": 0.120849609375}, "domain": "pixel"}, {"position": {"minX": 636.0, "minY": 420.25, "maxX": 648.0, "maxY": 454.75}, "class_id": 4, "box_caption": "pedestrian 0.119", "scores": {"class_score": 0.1192626953125}, "domain": "pixel"}, {"position": {"minX": 539.0, "minY": 396.25, "maxX": 561.0, "maxY": 466.75}, "class_id": 4, "box_caption": "pedestrian 0.112", "scores": {"class_score": 0.1123046875}, "domain": "pixel"}, {"position": {"minX": 659.0, "minY": 419.5, "maxX": 670.0, "maxY": 447.5}, "class_id": 4, "box_caption": "pedestrian 0.102", "scores": {"class_score": 0.101806640625}, "domain": "pixel"}, {"position": {"minX": 779.0, "minY": 428.0, "maxX": 800.0, "maxY": 447.5}, "class_id": 2, "box_caption": "car 0.075", "scores": {"class_score": 0.074951171875}, "domain": "pixel"}, {"position": {"minX": 319.0, "minY": 416.0, "maxX": 425.5, "maxY": 532.5}, "class_id": 4, "box_caption": "pedestrian 0.071", "scores": {"class_score": 0.07110595703125}, "domain": "pixel"}, {"position": {"minX": 867.5, "minY": 425.25, "maxX": 876.5, "maxY": 450.25}, "class_id": 4, "box_caption": "pedestrian 0.060", "scores": {"class_score": 0.060302734375}, "domain": "pixel"}, {"position": {"minX": 361.5, "minY": 410.25, "maxX": 377.0, "maxY": 426.75}, "class_id": 4, "box_caption": "pedestrian 0.058", "scores": {"class_score": 0.05792236328125}, "domain": "pixel"}, {"position": {"minX": 653.0, "minY": 419.75, "maxX": 667.0, "maxY": 449.25}, "class_id": 4, "box_caption": "pedestrian 0.048", "scores": {"class_score": 0.047515869140625}, "domain": "pixel"}, {"position": {"minX": 253.625, "minY": 408.75, "maxX": 423.0, "maxY": 549.0}, "class_id": 2, "box_caption": "car 0.036", "scores": {"class_score": 0.036285400390625}, "domain": "pixel"}, {"position": {"minX": 872.0, "minY": 420.75, "maxX": 885.0, "maxY": 447.25}, "class_id": 4, "box_caption": "pedestrian 0.036", "scores": {"class_score": 0.03607177734375}, "domain": "pixel"}, {"position": {"minX": 662.0, "minY": 420.25, "maxX": 672.0, "maxY": 445.75}, "class_id": 4, "box_caption": "pedestrian 0.035", "scores": {"class_score": 0.03466796875}, "domain": "pixel"}, {"position": {"minX": 923.5, "minY": 422.25, "maxX": 936.5, "maxY": 452.25}, "class_id": 4, "box_caption": "pedestrian 0.034", "scores": {"class_score": 0.033782958984375}, "domain": "pixel"}, {"position": {"minX": 31.15625, "minY": 517.5, "maxX": 40.34375, "maxY": 591.5}, "class_id": 2, "box_caption": "car 0.029", "scores": {"class_score": 0.028564453125}, "domain": "pixel"}, {"position": {"minX": 369.75, "minY": 409.25, "maxX": 384.75, "maxY": 426.25}, "class_id": 4, "box_caption": "pedestrian 0.028", "scores": {"class_score": 0.02813720703125}, "domain": "pixel"}, {"position": {"minX": 914.0, "minY": 420.25, "maxX": 927.0, "maxY": 449.75}, "class_id": 4, "box_caption": "pedestrian 0.027", "scores": {"class_score": 0.027008056640625}, "domain": "pixel"}, {"position": {"minX": 408.25, "minY": 417.0, "maxX": 428.75, "maxY": 471.5}, "class_id": 4, "box_caption": "pedestrian 0.026", "scores": {"class_score": 0.0260162353515625}, "domain": "pixel"}, {"position": {"minX": 776.0, "minY": 428.75, "maxX": 790.0, "maxY": 449.25}, "class_id": 2, "box_caption": "car 0.026", "scores": {"class_score": 0.02581787109375}, "domain": "pixel"}, {"position": {"minX": 1063.0, "minY": 409.75, "maxX": 1085.0, "maxY": 462.75}, "class_id": 4, "box_caption": "pedestrian 0.024", "scores": {"class_score": 0.0235137939453125}, "domain": "pixel"}, {"position": {"minX": 935.5, "minY": 410.0, "maxX": 960.5, "maxY": 486.0}, "class_id": 4, "box_caption": "pedestrian 0.022", "scores": {"class_score": 0.022064208984375}, "domain": "pixel"}, {"position": {"minX": 881.5, "minY": 423.5, "maxX": 890.5, "maxY": 448.5}, "class_id": 4, "box_caption": "pedestrian 0.020", "scores": {"class_score": 0.019744873046875}, "domain": "pixel"}, {"position": {"minX": 806.0, "minY": 429.25, "maxX": 826.0, "maxY": 447.25}, "class_id": 2, "box_caption": "car 0.016", "scores": {"class_score": 0.015625}, "domain": "pixel"}, {"position": {"minX": 353.75, "minY": 406.5, "maxX": 398.75, "maxY": 435.0}, "class_id": 4, "box_caption": "pedestrian 0.015", "scores": {"class_score": 0.0153656005859375}, "domain": "pixel"}, {"position": {"minX": 816.5, "minY": 428.5, "maxX": 831.5, "maxY": 448.0}, "class_id": 2, "box_caption": "car 0.013", "scores": {"class_score": 0.01303863525390625}, "domain": "pixel"}, {"position": {"minX": 670.0, "minY": 422.75, "maxX": 681.0, "maxY": 444.75}, "class_id": 4, "box_caption": "pedestrian 0.012", "scores": {"class_score": 0.01245880126953125}, "domain": "pixel"}, {"position": {"minX": 417.0, "minY": 413.0, "maxX": 463.5, "maxY": 474.5}, "class_id": 4, "box_caption": "pedestrian 0.012", "scores": {"class_score": 0.01224517822265625}, "domain": "pixel"}, {"position": {"minX": 538.5, "minY": 394.25, "maxX": 557.5, "maxY": 445.25}, "class_id": 4, "box_caption": "pedestrian 0.012", "scores": {"class_score": 0.012115478515625}, "domain": "pixel"}, {"position": {"minX": 817.0, "minY": 432.25, "maxX": 828.0, "maxY": 447.75}, "class_id": 4, "box_caption": "pedestrian 0.011", "scores": {"class_score": 0.01108551025390625}, "domain": "pixel"}, {"position": {"minX": 32.625, "minY": 515.5, "maxX": 43.5625, "maxY": 595.5}, "class_id": 2, "box_caption": "car 0.011", "scores": {"class_score": 0.0110626220703125}, "domain": "pixel"}, {"position": {"minX": 909.5, "minY": 419.0, "maxX": 918.5, "maxY": 447.0}, "class_id": 4, "box_caption": "pedestrian 0.010", "scores": {"class_score": 0.01047515869140625}, "domain": "pixel"}, {"position": {"minX": 931.0, "minY": 419.0, "maxX": 944.0, "maxY": 464.5}, "class_id": 4, "box_caption": "pedestrian 0.010", "scores": {"class_score": 0.0102081298828125}, "domain": "pixel"}, {"position": {"minX": 633.5, "minY": 423.5, "maxX": 646.5, "maxY": 459.5}, "class_id": 4, "box_caption": "pedestrian 0.010", "scores": {"class_score": 0.010009765625}, "domain": "pixel"}, {"position": {"minX": 1078.0, "minY": 408.75, "maxX": 1094.0, "maxY": 461.75}, "class_id": 4, "box_caption": "pedestrian 0.009", "scores": {"class_score": 0.0085906982421875}, "domain": "pixel"}, {"position": {"minX": 866.5, "minY": 422.25, "maxX": 875.5, "maxY": 445.25}, "class_id": 4, "box_caption": "pedestrian 0.008", "scores": {"class_score": 0.0079193115234375}, "domain": "pixel"}, {"position": {"minX": 827.5, "minY": 428.25, "maxX": 871.5, "maxY": 460.25}, "class_id": 4, "box_caption": "pedestrian 0.008", "scores": {"class_score": 0.007564544677734375}, "domain": "pixel"}, {"position": {"minX": 664.5, "minY": 421.5, "maxX": 675.5, "maxY": 445.0}, "class_id": 4, "box_caption": "pedestrian 0.007", "scores": {"class_score": 0.006938934326171875}, "domain": "pixel"}, {"position": {"minX": 325.5, "minY": 410.5, "maxX": 344.0, "maxY": 423.0}, "class_id": 4, "box_caption": "pedestrian 0.007", "scores": {"class_score": 0.006763458251953125}, "domain": "pixel"}, {"position": {"minX": 809.5, "minY": 432.25, "maxX": 822.5, "maxY": 446.75}, "class_id": 2, "box_caption": "car 0.006", "scores": {"class_score": 0.0064697265625}, "domain": "pixel"}, {"position": {"minX": 426.25, "minY": 413.0, "maxX": 447.25, "maxY": 475.5}, "class_id": 4, "box_caption": "pedestrian 0.006", "scores": {"class_score": 0.006420135498046875}, "domain": "pixel"}, {"position": {"minX": 1053.0, "minY": 405.75, "maxX": 1091.0, "maxY": 471.25}, "class_id": 4, "box_caption": "pedestrian 0.006", "scores": {"class_score": 0.006389617919921875}, "domain": "pixel"}, {"position": {"minX": 1071.0, "minY": 407.25, "maxX": 1091.0, "maxY": 461.75}, "class_id": 2, "box_caption": "car 0.006", "scores": {"class_score": 0.00565338134765625}, "domain": "pixel"}, {"position": {"minX": 462.5, "minY": 415.5, "maxX": 480.5, "maxY": 449.5}, "class_id": 4, "box_caption": "pedestrian 0.005", "scores": {"class_score": 0.00545501708984375}, "domain": "pixel"}, {"position": {"minX": 364.75, "minY": 415.25, "maxX": 380.75, "maxY": 426.75}, "class_id": 4, "box_caption": "pedestrian 0.005", "scores": {"class_score": 0.005405426025390625}, "domain": "pixel"}, {"position": {"minX": 637.0, "minY": 419.25, "maxX": 646.0, "maxY": 446.25}, "class_id": 4, "box_caption": "pedestrian 0.005", "scores": {"class_score": 0.005275726318359375}, "domain": "pixel"}, {"position": {"minX": 353.75, "minY": 406.5, "maxX": 398.75, "maxY": 435.0}, "class_id": 2, "box_caption": "car 0.005", "scores": {"class_score": 0.0052490234375}, "domain": "pixel"}, {"position": {"minX": 439.0, "minY": 413.75, "maxX": 492.0, "maxY": 476.75}, "class_id": 4, "box_caption": "pedestrian 0.005", "scores": {"class_score": 0.005077362060546875}, "domain": "pixel"}, {"position": {"minX": 32.5, "minY": 386.0, "maxX": 383.5, "maxY": 591.0}, "class_id": 4, "box_caption": "pedestrian 0.005", "scores": {"class_score": 0.00492095947265625}, "domain": "pixel"}, {"position": {"minX": 358.25, "minY": 408.0, "maxX": 388.25, "maxY": 429.0}, "class_id": 4, "box_caption": "pedestrian 0.005", "scores": {"class_score": 0.004802703857421875}, "domain": "pixel"}, {"position": {"minX": 822.5, "minY": 429.75, "maxX": 841.5, "maxY": 448.25}, "class_id": 2, "box_caption": "car 0.005", "scores": {"class_score": 0.004688262939453125}, "domain": "pixel"}, {"position": {"minX": 871.0, "minY": 429.0, "maxX": 883.0, "maxY": 454.5}, "class_id": 4, "box_caption": "pedestrian 0.005", "scores": {"class_score": 0.004680633544921875}, "domain": "pixel"}, {"position": {"minX": 785.0, "minY": 427.0, "maxX": 811.0, "maxY": 448.0}, "class_id": 7, "box_caption": "truck 0.004", "scores": {"class_score": 0.00433349609375}, "domain": "pixel"}, {"position": {"minX": 406.0, "minY": 411.75, "maxX": 450.0, "maxY": 480.75}, "class_id": 4, "box_caption": "pedestrian 0.004", "scores": {"class_score": 0.00421905517578125}, "domain": "pixel"}, {"position": {"minX": 673.0, "minY": 426.75, "maxX": 685.0, "maxY": 444.75}, "class_id": 4, "box_caption": "pedestrian 0.004", "scores": {"class_score": 0.0041961669921875}, "domain": "pixel"}, {"position": {"minX": 876.0, "minY": 423.75, "maxX": 887.0, "maxY": 448.75}, "class_id": 7, "box_caption": "truck 0.004", "scores": {"class_score": 0.00418853759765625}, "domain": "pixel"}, {"position": {"minX": 935.0, "minY": 402.0, "maxX": 975.0, "maxY": 492.5}, "class_id": 2, "box_caption": "car 0.004", "scores": {"class_score": 0.00411224365234375}, "domain": "pixel"}, {"position": {"minX": 934.5, "minY": 404.0, "maxX": 975.5, "maxY": 491.0}, "class_id": 7, "box_caption": "truck 0.004", "scores": {"class_score": 0.004058837890625}, "domain": "pixel"}, {"position": {"minX": 920.0, "minY": 418.5, "maxX": 934.0, "maxY": 451.0}, "class_id": 7, "box_caption": "truck 0.004", "scores": {"class_score": 0.004024505615234375}, "domain": "pixel"}, {"position": {"minX": 411.25, "minY": 412.0, "maxX": 444.25, "maxY": 481.0}, "class_id": 2, "box_caption": "car 0.004", "scores": {"class_score": 0.003932952880859375}, "domain": "pixel"}, {"position": {"minX": 932.5, "minY": 430.25, "maxX": 942.5, "maxY": 453.25}, "class_id": 4, "box_caption": "pedestrian 0.004", "scores": {"class_score": 0.0039043426513671875}, "domain": "pixel"}, {"position": {"minX": 1061.0, "minY": 420.5, "maxX": 1079.0, "maxY": 464.0}, "class_id": 4, "box_caption": "pedestrian 0.004", "scores": {"class_score": 0.0038242340087890625}, "domain": "pixel"}, {"position": {"minX": 825.5, "minY": 429.5, "maxX": 869.5, "maxY": 460.0}, "class_id": 7, "box_caption": "truck 0.004", "scores": {"class_score": 0.003803253173828125}, "domain": "pixel"}, {"position": {"minX": 818.5, "minY": 431.5, "maxX": 833.5, "maxY": 451.0}, "class_id": 2, "box_caption": "car 0.004", "scores": {"class_score": 0.0037708282470703125}, "domain": "pixel"}, {"position": {"minX": 875.5, "minY": 422.5, "maxX": 886.5, "maxY": 450.5}, "class_id": 2, "box_caption": "car 0.004", "scores": {"class_score": 0.00376129150390625}, "domain": "pixel"}, {"position": {"minX": 483.25, "minY": 416.0, "maxX": 499.75, "maxY": 448.0}, "class_id": 4, "box_caption": "pedestrian 0.004", "scores": {"class_score": 0.0036296844482421875}, "domain": "pixel"}, {"position": {"minX": 906.0, "minY": 422.5, "maxX": 926.0, "maxY": 448.5}, "class_id": 4, "box_caption": "pedestrian 0.004", "scores": {"class_score": 0.0036182403564453125}, "domain": "pixel"}, {"position": {"minX": 473.25, "minY": 413.5, "maxX": 493.25, "maxY": 467.5}, "class_id": 4, "box_caption": "pedestrian 0.004", "scores": {"class_score": 0.0035724639892578125}, "domain": "pixel"}, {"position": {"minX": 934.5, "minY": 409.75, "maxX": 955.5, "maxY": 451.25}, "class_id": 4, "box_caption": "pedestrian 0.004", "scores": {"class_score": 0.0035343170166015625}, "domain": "pixel"}, {"position": {"minX": 484.5, "minY": 415.5, "maxX": 501.0, "maxY": 436.0}, "class_id": 4, "box_caption": "pedestrian 0.004", "scores": {"class_score": 0.003528594970703125}, "domain": "pixel"}, {"position": {"minX": 865.5, "minY": 423.5, "maxX": 890.5, "maxY": 449.5}, "class_id": 2, "box_caption": "car 0.003", "scores": {"class_score": 0.00345611572265625}, "domain": "pixel"}, {"position": {"minX": 906.5, "minY": 415.25, "maxX": 915.5, "maxY": 443.75}, "class_id": 4, "box_caption": "pedestrian 0.003", "scores": {"class_score": 0.0034542083740234375}, "domain": "pixel"}, {"position": {"minX": 785.5, "minY": 429.0, "maxX": 810.5, "maxY": 448.5}, "class_id": 4, "box_caption": "pedestrian 0.003", "scores": {"class_score": 0.003398895263671875}, "domain": "pixel"}, {"position": {"minX": 875.0, "minY": 423.0, "maxX": 886.0, "maxY": 451.0}, "class_id": 5, "box_caption": "rider 0.003", "scores": {"class_score": 0.0032901763916015625}, "domain": "pixel"}, {"position": {"minX": 32.375, "minY": 386.0, "maxX": 383.5, "maxY": 591.0}, "class_id": 7, "box_caption": "truck 0.003", "scores": {"class_score": 0.003246307373046875}, "domain": "pixel"}, {"position": {"minX": 827.0, "minY": 429.75, "maxX": 869.0, "maxY": 459.75}, "class_id": 1, "box_caption": "bus 0.003", "scores": {"class_score": 0.00324249267578125}, "domain": "pixel"}, {"position": {"minX": 936.5, "minY": 404.75, "maxX": 974.5, "maxY": 490.25}, "class_id": 1, "box_caption": "bus 0.003", "scores": {"class_score": 0.003124237060546875}, "domain": "pixel"}, {"position": {"minX": 375.0, "minY": 411.75, "maxX": 390.0, "maxY": 428.25}, "class_id": 4, "box_caption": "pedestrian 0.003", "scores": {"class_score": 0.003093719482421875}, "domain": "pixel"}, {"position": {"minX": 806.0, "minY": 429.75, "maxX": 826.0, "maxY": 446.75}, "class_id": 4, "box_caption": "pedestrian 0.003", "scores": {"class_score": 0.003040313720703125}, "domain": "pixel"}, {"position": {"minX": 920.0, "minY": 417.75, "maxX": 934.0, "maxY": 450.25}, "class_id": 5, "box_caption": "rider 0.003", "scores": {"class_score": 0.00302886962890625}, "domain": "pixel"}, {"position": {"minX": 305.25, "minY": 418.25, "maxX": 429.75, "maxY": 537.5}, "class_id": 7, "box_caption": "truck 0.003", "scores": {"class_score": 0.0029659271240234375}, "domain": "pixel"}, {"position": {"minX": 373.0, "minY": 414.75, "maxX": 386.0, "maxY": 427.75}, "class_id": 4, "box_caption": "pedestrian 0.003", "scores": {"class_score": 0.0029048919677734375}, "domain": "pixel"}, {"position": {"minX": 726.5, "minY": 426.25, "maxX": 732.5, "maxY": 447.25}, "class_id": 4, "box_caption": "pedestrian 0.003", "scores": {"class_score": 0.002887725830078125}, "domain": "pixel"}, {"position": {"minX": 914.5, "minY": 414.25, "maxX": 945.5, "maxY": 457.25}, "class_id": 4, "box_caption": "pedestrian 0.003", "scores": {"class_score": 0.00286865234375}, "domain": "pixel"}, {"position": {"minX": 657.5, "minY": 423.5, "maxX": 671.5, "maxY": 453.5}, "class_id": 4, "box_caption": "pedestrian 0.003", "scores": {"class_score": 0.0028553009033203125}, "domain": "pixel"}, {"position": {"minX": 309.5, "minY": 417.75, "maxX": 428.0, "maxY": 536.5}, "class_id": 0, "box_caption": "bicycle 0.003", "scores": {"class_score": 0.002796173095703125}, "domain": "pixel"}, {"position": {"minX": 32.375, "minY": 386.0, "maxX": 383.5, "maxY": 591.0}, "class_id": 1, "box_caption": "bus 0.003", "scores": {"class_score": 0.002777099609375}, "domain": "pixel"}, {"position": {"minX": 457.0, "minY": 414.0, "maxX": 511.0, "maxY": 472.0}, "class_id": 4, "box_caption": "pedestrian 0.003", "scores": {"class_score": 0.0027637481689453125}, "domain": "pixel"}, {"position": {"minX": 503.5, "minY": 401.0, "maxX": 549.5, "maxY": 469.0}, "class_id": 4, "box_caption": "pedestrian 0.003", "scores": {"class_score": 0.0026950836181640625}, "domain": "pixel"}, {"position": {"minX": 30.625, "minY": 386.5, "maxX": 385.5, "maxY": 590.0}, "class_id": 6, "box_caption": "train 0.003", "scores": {"class_score": 0.0026702880859375}, "domain": "pixel"}, {"position": {"minX": 30.625, "minY": 386.5, "maxX": 385.5, "maxY": 590.0}, "class_id": 3, "box_caption": "motorcycle 0.003", "scores": {"class_score": 0.0026702880859375}, "domain": "pixel"}, {"position": {"minX": 826.5, "minY": 429.5, "maxX": 869.5, "maxY": 460.0}, "class_id": 0, "box_caption": "bicycle 0.003", "scores": {"class_score": 0.0026683807373046875}, "domain": "pixel"}, {"position": {"minX": 754.5, "minY": 428.0, "maxX": 783.5, "maxY": 452.5}, "class_id": 7, "box_caption": "truck 0.003", "scores": {"class_score": 0.00266265869140625}, "domain": "pixel"}, {"position": {"minX": 342.75, "minY": 404.0, "maxX": 404.25, "maxY": 445.0}, "class_id": 4, "box_caption": "pedestrian 0.003", "scores": {"class_score": 0.0026607513427734375}, "domain": "pixel"}, {"position": {"minX": 342.75, "minY": 404.0, "maxX": 404.25, "maxY": 445.0}, "class_id": 2, "box_caption": "car 0.003", "scores": {"class_score": 0.0026531219482421875}, "domain": "pixel"}, {"position": {"minX": 309.5, "minY": 417.75, "maxX": 428.0, "maxY": 536.5}, "class_id": 1, "box_caption": "bus 0.003", "scores": {"class_score": 0.00264739990234375}, "domain": "pixel"}, {"position": {"minX": 648.0, "minY": 430.0, "maxX": 658.0, "maxY": 460.0}, "class_id": 4, "box_caption": "pedestrian 0.003", "scores": {"class_score": 0.0026416778564453125}, "domain": "pixel"}, {"position": {"minX": 421.75, "minY": 410.25, "maxX": 443.75, "maxY": 463.25}, "class_id": 4, "box_caption": "pedestrian 0.003", "scores": {"class_score": 0.002620697021484375}, "domain": "pixel"}, {"position": {"minX": 913.0, "minY": 428.5, "maxX": 924.0, "maxY": 449.5}, "class_id": 4, "box_caption": "pedestrian 0.003", "scores": {"class_score": 0.00258636474609375}, "domain": "pixel"}, {"position": {"minX": 529.5, "minY": 388.5, "maxX": 558.5, "maxY": 461.5}, "class_id": 4, "box_caption": "pedestrian 0.003", "scores": {"class_score": 0.0025348663330078125}, "domain": "pixel"}, {"position": {"minX": 418.5, "minY": 412.75, "maxX": 442.5, "maxY": 478.25}, "class_id": 7, "box_caption": "truck 0.003", "scores": {"class_score": 0.0025157928466796875}, "domain": "pixel"}, {"position": {"minX": 410.25, "minY": 433.0, "maxX": 428.75, "maxY": 498.5}, "class_id": 4, "box_caption": "pedestrian 0.003", "scores": {"class_score": 0.00251007080078125}, "domain": "pixel"}, {"position": {"minX": 826.5, "minY": 429.5, "maxX": 869.5, "maxY": 460.0}, "class_id": 5, "box_caption": "rider 0.002", "scores": {"class_score": 0.0023365020751953125}, "domain": "pixel"}, {"position": {"minX": 826.5, "minY": 429.5, "maxX": 869.5, "maxY": 460.0}, "class_id": 6, "box_caption": "train 0.002", "scores": {"class_score": 0.0023288726806640625}, "domain": "pixel"}, {"position": {"minX": 30.625, "minY": 386.5, "maxX": 385.5, "maxY": 590.0}, "class_id": 5, "box_caption": "rider 0.002", "scores": {"class_score": 0.0022754669189453125}, "domain": "pixel"}, {"position": {"minX": 865.5, "minY": 423.5, "maxX": 890.5, "maxY": 449.5}, "class_id": 4, "box_caption": "pedestrian 0.002", "scores": {"class_score": 0.0022735595703125}, "domain": "pixel"}, {"position": {"minX": 30.625, "minY": 386.5, "maxX": 385.5, "maxY": 590.0}, "class_id": 0, "box_caption": "bicycle 0.002", "scores": {"class_score": 0.00226593017578125}, "domain": "pixel"}, {"position": {"minX": 315.0, "minY": 398.5, "maxX": 415.5, "maxY": 477.0}, "class_id": 2, "box_caption": "car 0.002", "scores": {"class_score": 0.0022640228271484375}, "domain": "pixel"}, {"position": {"minX": 827.0, "minY": 429.75, "maxX": 869.0, "maxY": 459.75}, "class_id": 3, "box_caption": "motorcycle 0.002", "scores": {"class_score": 0.002197265625}, "domain": "pixel"}, {"position": {"minX": 1039.0, "minY": 413.0, "maxX": 1085.0, "maxY": 464.5}, "class_id": 4, "box_caption": "pedestrian 0.002", "scores": {"class_score": 0.002193450927734375}, "domain": "pixel"}, {"position": {"minX": 904.0, "minY": 405.25, "maxX": 915.0, "maxY": 441.25}, "class_id": 4, "box_caption": "pedestrian 0.002", "scores": {"class_score": 0.002155303955078125}, "domain": "pixel"}, {"position": {"minX": 1001.5, "minY": 419.0, "maxX": 1016.5, "maxY": 440.5}, "class_id": 4, "box_caption": "pedestrian 0.002", "scores": {"class_score": 0.002155303955078125}, "domain": "pixel"}, {"position": {"minX": 646.5, "minY": 417.5, "maxX": 660.5, "maxY": 452.5}, "class_id": 5, "box_caption": "rider 0.002", "scores": {"class_score": 0.002132415771484375}, "domain": "pixel"}, {"position": {"minX": 787.5, "minY": 425.25, "maxX": 814.5, "maxY": 442.75}, "class_id": 2, "box_caption": "car 0.002", "scores": {"class_score": 0.0021152496337890625}, "domain": "pixel"}, {"position": {"minX": 1025.0, "minY": 427.0, "maxX": 1057.0, "maxY": 462.5}, "class_id": 2, "box_caption": "car 0.002", "scores": {"class_score": 0.0020923614501953125}, "domain": "pixel"}, {"position": {"minX": 309.5, "minY": 417.75, "maxX": 428.0, "maxY": 536.5}, "class_id": 6, "box_caption": "train 0.002", "scores": {"class_score": 0.0020809173583984375}, "domain": "pixel"}, {"position": {"minX": 755.0, "minY": 427.0, "maxX": 784.0, "maxY": 453.0}, "class_id": 4, "box_caption": "pedestrian 0.002", "scores": {"class_score": 0.0020351409912109375}, "domain": "pixel"}, {"position": {"minX": 1029.0, "minY": 442.75, "maxX": 1039.0, "maxY": 489.25}, "class_id": 2, "box_caption": "car 0.002", "scores": {"class_score": 0.0020351409912109375}, "domain": "pixel"}, {"position": {"minX": 1021.5, "minY": 425.75, "maxX": 1066.0, "maxY": 482.75}, "class_id": 2, "box_caption": "car 0.002", "scores": {"class_score": 0.002010345458984375}, "domain": "pixel"}, {"position": {"minX": 309.5, "minY": 417.75, "maxX": 428.0, "maxY": 536.5}, "class_id": 3, "box_caption": "motorcycle 0.002", "scores": {"class_score": 0.0020008087158203125}, "domain": "pixel"}, {"position": {"minX": 754.5, "minY": 428.0, "maxX": 783.5, "maxY": 452.5}, "class_id": 1, "box_caption": "bus 0.002", "scores": {"class_score": 0.001995086669921875}, "domain": "pixel"}, {"position": {"minX": 257.25, "minY": 391.5, "maxX": 420.25, "maxY": 502.0}, "class_id": 2, "box_caption": "car 0.002", "scores": {"class_score": 0.001956939697265625}, "domain": "pixel"}, {"position": {"minX": 309.5, "minY": 417.75, "maxX": 428.0, "maxY": 536.5}, "class_id": 5, "box_caption": "rider 0.002", "scores": {"class_score": 0.0019235610961914062}, "domain": "pixel"}, {"position": {"minX": 30.3125, "minY": 528.0, "maxX": 38.6875, "maxY": 581.0}, "class_id": 2, "box_caption": "car 0.002", "scores": {"class_score": 0.0019207000732421875}, "domain": "pixel"}, {"position": {"minX": 935.5, "minY": 404.0, "maxX": 974.5, "maxY": 490.5}, "class_id": 5, "box_caption": "rider 0.002", "scores": {"class_score": 0.0019092559814453125}, "domain": "pixel"}, {"position": {"minX": 823.5, "minY": 426.0, "maxX": 862.5, "maxY": 448.5}, "class_id": 2, "box_caption": "car 0.002", "scores": {"class_score": 0.001865386962890625}, "domain": "pixel"}, {"position": {"minX": 999.0, "minY": 417.0, "maxX": 1013.0, "maxY": 442.0}, "class_id": 4, "box_caption": "pedestrian 0.002", "scores": {"class_score": 0.0018091201782226562}, "domain": "pixel"}, {"position": {"minX": 1071.0, "minY": 407.5, "maxX": 1091.0, "maxY": 461.0}, "class_id": 5, "box_caption": "rider 0.002", "scores": {"class_score": 0.0017986297607421875}, "domain": "pixel"}, {"position": {"minX": 821.0, "minY": 437.75, "maxX": 831.0, "maxY": 452.75}, "class_id": 2, "box_caption": "car 0.002", "scores": {"class_score": 0.001758575439453125}, "domain": "pixel"}, {"position": {"minX": 325.0, "minY": 412.25, "maxX": 343.0, "maxY": 428.25}, "class_id": 4, "box_caption": "pedestrian 0.002", "scores": {"class_score": 0.0017442703247070312}, "domain": "pixel"}, {"position": {"minX": 785.0, "minY": 427.0, "maxX": 811.0, "maxY": 448.0}, "class_id": 1, "box_caption": "bus 0.002", "scores": {"class_score": 0.0016908645629882812}, "domain": "pixel"}, {"position": {"minX": 646.0, "minY": 419.5, "maxX": 680.0, "maxY": 451.5}, "class_id": 4, "box_caption": "pedestrian 0.002", "scores": {"class_score": 0.0016641616821289062}, "domain": "pixel"}, {"position": {"minX": 779.0, "minY": 428.0, "maxX": 800.0, "maxY": 447.5}, "class_id": 4, "box_caption": "pedestrian 0.002", "scores": {"class_score": 0.0016498565673828125}, "domain": "pixel"}, {"position": {"minX": 636.0, "minY": 420.5, "maxX": 648.0, "maxY": 454.5}, "class_id": 2, "box_caption": "car 0.002", "scores": {"class_score": 0.0016450881958007812}, "domain": "pixel"}, {"position": {"minX": 1071.0, "minY": 407.5, "maxX": 1091.0, "maxY": 463.0}, "class_id": 7, "box_caption": "truck 0.002", "scores": {"class_score": 0.0016326904296875}, "domain": "pixel"}, {"position": {"minX": 935.5, "minY": 404.0, "maxX": 974.5, "maxY": 490.5}, "class_id": 0, "box_caption": "bicycle 0.002", "scores": {"class_score": 0.0016326904296875}, "domain": "pixel"}, {"position": {"minX": 888.5, "minY": 423.25, "maxX": 895.5, "maxY": 444.25}, "class_id": 4, "box_caption": "pedestrian 0.002", "scores": {"class_score": 0.0016317367553710938}, "domain": "pixel"}, {"position": {"minX": 876.0, "minY": 428.75, "maxX": 887.0, "maxY": 454.25}, "class_id": 4, "box_caption": "pedestrian 0.002", "scores": {"class_score": 0.0016117095947265625}, "domain": "pixel"}, {"position": {"minX": 876.0, "minY": 423.75, "maxX": 887.0, "maxY": 448.75}, "class_id": 1, "box_caption": "bus 0.002", "scores": {"class_score": 0.001590728759765625}, "domain": "pixel"}, {"position": {"minX": 412.75, "minY": 424.5, "maxX": 432.75, "maxY": 463.5}, "class_id": 4, "box_caption": "pedestrian 0.002", "scores": {"class_score": 0.0015497207641601562}, "domain": "pixel"}, {"position": {"minX": 935.5, "minY": 404.0, "maxX": 974.5, "maxY": 490.5}, "class_id": 3, "box_caption": "motorcycle 0.002", "scores": {"class_score": 0.0015468597412109375}, "domain": "pixel"}, {"position": {"minX": 345.5, "minY": 406.5, "maxX": 454.0, "maxY": 483.5}, "class_id": 2, "box_caption": "car 0.002", "scores": {"class_score": 0.0015316009521484375}, "domain": "pixel"}, {"position": {"minX": 813.5, "minY": 426.25, "maxX": 826.5, "maxY": 441.75}, "class_id": 2, "box_caption": "car 0.002", "scores": {"class_score": 0.0015192031860351562}, "domain": "pixel"}, {"position": {"minX": 1029.0, "minY": 442.75, "maxX": 1039.0, "maxY": 489.25}, "class_id": 4, "box_caption": "pedestrian 0.001", "scores": {"class_score": 0.0014905929565429688}, "domain": "pixel"}, {"position": {"minX": 358.25, "minY": 405.75, "maxX": 378.25, "maxY": 427.25}, "class_id": 4, "box_caption": "pedestrian 0.001", "scores": {"class_score": 0.0014867782592773438}, "domain": "pixel"}, {"position": {"minX": 873.5, "minY": 424.0, "maxX": 882.5, "maxY": 452.0}, "class_id": 2, "box_caption": "car 0.001", "scores": {"class_score": 0.0014476776123046875}, "domain": "pixel"}, {"position": {"minX": 754.5, "minY": 428.0, "maxX": 783.5, "maxY": 452.5}, "class_id": 0, "box_caption": "bicycle 0.001", "scores": {"class_score": 0.001438140869140625}, "domain": "pixel"}, {"position": {"minX": 418.0, "minY": 413.75, "maxX": 442.0, "maxY": 479.25}, "class_id": 5, "box_caption": "rider 0.001", "scores": {"class_score": 0.0014352798461914062}, "domain": "pixel"}, {"position": {"minX": 1061.0, "minY": 421.25, "maxX": 1079.0, "maxY": 463.75}, "class_id": 2, "box_caption": "car 0.001", "scores": {"class_score": 0.0014247894287109375}, "domain": "pixel"}, {"position": {"minX": 1039.0, "minY": 413.0, "maxX": 1085.0, "maxY": 464.5}, "class_id": 2, "box_caption": "car 0.001", "scores": {"class_score": 0.0014162063598632812}, "domain": "pixel"}, {"position": {"minX": 639.0, "minY": 421.25, "maxX": 651.0, "maxY": 456.25}, "class_id": 2, "box_caption": "car 0.001", "scores": {"class_score": 0.0013971328735351562}, "domain": "pixel"}, {"position": {"minX": 646.5, "minY": 418.0, "maxX": 660.5, "maxY": 457.5}, "class_id": 2, "box_caption": "car 0.001", "scores": {"class_score": 0.0013952255249023438}, "domain": "pixel"}, {"position": {"minX": 817.0, "minY": 432.25, "maxX": 828.0, "maxY": 447.75}, "class_id": 7, "box_caption": "truck 0.001", "scores": {"class_score": 0.001392364501953125}, "domain": "pixel"}, {"position": {"minX": 1028.0, "minY": 425.25, "maxX": 1046.0, "maxY": 472.25}, "class_id": 4, "box_caption": "pedestrian 0.001", "scores": {"class_score": 0.001384735107421875}, "domain": "pixel"}, {"position": {"minX": 1075.0, "minY": 417.75, "maxX": 1091.0, "maxY": 457.75}, "class_id": 4, "box_caption": "pedestrian 0.001", "scores": {"class_score": 0.0013713836669921875}, "domain": "pixel"}, {"position": {"minX": 821.5, "minY": 420.25, "maxX": 866.5, "maxY": 455.75}, "class_id": 2, "box_caption": "car 0.001", "scores": {"class_score": 0.001338958740234375}, "domain": "pixel"}, {"position": {"minX": 1071.0, "minY": 407.5, "maxX": 1091.0, "maxY": 463.0}, "class_id": 0, "box_caption": "bicycle 0.001", "scores": {"class_score": 0.0013332366943359375}, "domain": "pixel"}, {"position": {"minX": 1063.0, "minY": 409.75, "maxX": 1085.0, "maxY": 462.75}, "class_id": 2, "box_caption": "car 0.001", "scores": {"class_score": 0.0013303756713867188}, "domain": "pixel"}, {"position": {"minX": 754.5, "minY": 428.0, "maxX": 783.5, "maxY": 452.5}, "class_id": 3, "box_caption": "motorcycle 0.001", "scores": {"class_score": 0.0013303756713867188}, "domain": "pixel"}, {"position": {"minX": 1055.0, "minY": 420.75, "maxX": 1075.0, "maxY": 474.75}, "class_id": 4, "box_caption": "pedestrian 0.001", "scores": {"class_score": 0.0013179779052734375}, "domain": "pixel"}, {"position": {"minX": 418.0, "minY": 413.75, "maxX": 442.0, "maxY": 479.25}, "class_id": 0, "box_caption": "bicycle 0.001", "scores": {"class_score": 0.0013017654418945312}, "domain": "pixel"}, {"position": {"minX": 919.0, "minY": 422.75, "maxX": 935.0, "maxY": 460.75}, "class_id": 4, "box_caption": "pedestrian 0.001", "scores": {"class_score": 0.0012979507446289062}, "domain": "pixel"}, {"position": {"minX": 873.0, "minY": 421.25, "maxX": 885.0, "maxY": 451.25}, "class_id": 7, "box_caption": "truck 0.001", "scores": {"class_score": 0.001262664794921875}, "domain": "pixel"}, {"position": {"minX": 817.0, "minY": 432.25, "maxX": 828.0, "maxY": 447.75}, "class_id": 5, "box_caption": "rider 0.001", "scores": {"class_score": 0.0012569427490234375}, "domain": "pixel"}, {"position": {"minX": 28.71875, "minY": 496.5, "maxX": 39.90625, "maxY": 586.5}, "class_id": 2, "box_caption": "car 0.001", "scores": {"class_score": 0.00122833251953125}, "domain": "pixel"}, {"position": {"minX": 754.5, "minY": 428.0, "maxX": 783.5, "maxY": 452.5}, "class_id": 6, "box_caption": "train 0.001", "scores": {"class_score": 0.0012111663818359375}, "domain": "pixel"}, {"position": {"minX": 754.5, "minY": 428.0, "maxX": 783.5, "maxY": 452.5}, "class_id": 5, "box_caption": "rider 0.001", "scores": {"class_score": 0.0012111663818359375}, "domain": "pixel"}, {"position": {"minX": 1028.0, "minY": 425.25, "maxX": 1046.0, "maxY": 472.25}, "class_id": 2, "box_caption": "car 0.001", "scores": {"class_score": 0.0012054443359375}, "domain": "pixel"}, {"position": {"minX": 462.25, "minY": 414.0, "maxX": 484.25, "maxY": 472.0}, "class_id": 7, "box_caption": "truck 0.001", "scores": {"class_score": 0.0011854171752929688}, "domain": "pixel"}, {"position": {"minX": 345.5, "minY": 406.5, "maxX": 454.0, "maxY": 483.5}, "class_id": 4, "box_caption": "pedestrian 0.001", "scores": {"class_score": 0.00115203857421875}, "domain": "pixel"}, {"position": {"minX": 817.0, "minY": 432.25, "maxX": 828.0, "maxY": 447.75}, "class_id": 1, "box_caption": "bus 0.001", "scores": {"class_score": 0.0011472702026367188}, "domain": "pixel"}, {"position": {"minX": 906.5, "minY": 414.0, "maxX": 933.5, "maxY": 445.0}, "class_id": 4, "box_caption": "pedestrian 0.001", "scores": {"class_score": 0.0011463165283203125}, "domain": "pixel"}, {"position": {"minX": 920.0, "minY": 418.5, "maxX": 934.0, "maxY": 451.0}, "class_id": 0, "box_caption": "bicycle 0.001", "scores": {"class_score": 0.0011434555053710938}, "domain": "pixel"}, {"position": {"minX": 282.5, "minY": 402.25, "maxX": 391.5, "maxY": 476.75}, "class_id": 2, "box_caption": "car 0.001", "scores": {"class_score": 0.001132965087890625}, "domain": "pixel"}, {"position": {"minX": 1024.0, "minY": 430.0, "maxX": 1048.0, "maxY": 485.0}, "class_id": 2, "box_caption": "car 0.001", "scores": {"class_score": 0.001129150390625}, "domain": "pixel"}, {"position": {"minX": 1020.0, "minY": 421.5, "maxX": 1074.0, "maxY": 466.5}, "class_id": 2, "box_caption": "car 0.001", "scores": {"class_score": 0.0011119842529296875}, "domain": "pixel"}, {"position": {"minX": 646.5, "minY": 417.75, "maxX": 660.5, "maxY": 457.75}, "class_id": 7, "box_caption": "truck 0.001", "scores": {"class_score": 0.0011014938354492188}, "domain": "pixel"}, {"position": {"minX": 867.5, "minY": 425.25, "maxX": 876.5, "maxY": 450.25}, "class_id": 2, "box_caption": "car 0.001", "scores": {"class_score": 0.0011005401611328125}, "domain": "pixel"}, {"position": {"minX": 917.5, "minY": 417.0, "maxX": 934.5, "maxY": 454.0}, "class_id": 2, "box_caption": "car 0.001", "scores": {"class_score": 0.0011005401611328125}, "domain": "pixel"}, {"position": {"minX": 921.5, "minY": 415.0, "maxX": 932.5, "maxY": 436.5}, "class_id": 4, "box_caption": "pedestrian 0.001", "scores": {"class_score": 0.0010995864868164062}, "domain": "pixel"}, {"position": {"minX": 936.5, "minY": 406.25, "maxX": 975.5, "maxY": 454.25}, "class_id": 4, "box_caption": "pedestrian 0.001", "scores": {"class_score": 0.0010852813720703125}, "domain": "pixel"}, {"position": {"minX": 1074.0, "minY": 416.75, "maxX": 1092.0, "maxY": 476.75}, "class_id": 4, "box_caption": "pedestrian 0.001", "scores": {"class_score": 0.0010700225830078125}, "domain": "pixel"}, {"position": {"minX": 857.5, "minY": 428.75, "maxX": 869.5, "maxY": 449.25}, "class_id": 4, "box_caption": "pedestrian 0.001", "scores": {"class_score": 0.0010671615600585938}, "domain": "pixel"}, {"position": {"minX": 538.0, "minY": 393.5, "maxX": 560.0, "maxY": 467.0}, "class_id": 7, "box_caption": "truck 0.001", "scores": {"class_score": 0.0010356903076171875}, "domain": "pixel"}, {"position": {"minX": 646.5, "minY": 418.0, "maxX": 660.5, "maxY": 457.5}, "class_id": 0, "box_caption": "bicycle 0.001", "scores": {"class_score": 0.0010328292846679688}, "domain": "pixel"}, {"position": {"minX": 408.5, "minY": 430.5, "maxX": 427.0, "maxY": 466.0}, "class_id": 4, "box_caption": "pedestrian 0.001", "scores": {"class_score": 0.0010309219360351562}, "domain": "pixel"}, {"position": {"minX": 1027.0, "minY": 434.25, "maxX": 1043.0, "maxY": 485.25}, "class_id": 4, "box_caption": "pedestrian 0.001", "scores": {"class_score": 0.0010290145874023438}, "domain": "pixel"}, {"position": {"minX": 791.0, "minY": 432.75, "maxX": 815.0, "maxY": 449.25}, "class_id": 2, "box_caption": "car 0.001", "scores": {"class_score": 0.001026153564453125}, "domain": "pixel"}, {"position": {"minX": 304.25, "minY": 393.0, "maxX": 460.75, "maxY": 513.0}, "class_id": 2, "box_caption": "car 0.001", "scores": {"class_score": 0.001026153564453125}, "domain": "pixel"}, {"position": {"minX": 1054.0, "minY": 423.5, "maxX": 1074.0, "maxY": 473.0}, "class_id": 2, "box_caption": "car 0.001", "scores": {"class_score": 0.0010204315185546875}, "domain": "pixel"}, {"position": {"minX": 875.5, "minY": 422.5, "maxX": 886.5, "maxY": 450.5}, "class_id": 0, "box_caption": "bicycle 0.001", "scores": {"class_score": 0.0010128021240234375}, "domain": "pixel"}, {"position": {"minX": 935.5, "minY": 404.0, "maxX": 974.5, "maxY": 490.5}, "class_id": 6, "box_caption": "train 0.001", "scores": {"class_score": 0.001010894775390625}, "domain": "pixel"}, {"position": {"minX": 636.5, "minY": 416.5, "maxX": 666.5, "maxY": 457.5}, "class_id": 4, "box_caption": "pedestrian 0.001", "scores": {"class_score": 0.001007080078125}, "domain": "pixel"}], "class_labels": {"0": "bicycle", "1": "bus", "2": "car", "3": "motorcycle", "4": "pedestrian", "5": "rider", "6": "train", "7": "truck"}}